Workbook

Sheet AREAS
A1: ID | B1: Nome | C1: Links | D1: [ON / OFF] | E1: Status da área | F1: # UAU LAND-BANK | G1: # Workflow | H1: Empresa UAU | I1: Obra UAU | J1: Código Modelo | K1: Regional | L1: Cidade | M1: UF | N1: Empreendimento | O1: Tipo de Contrato | P1: Valor de Compra da Área - Aquisição (R$mm) | Q1: Tipo | R1: Projeto Feito | S1: Year | T1: Data de Lançamento | U1: Participação Buriti | V1: Participação Terreneiro (não paga obra) | W1: Participação Buriti + Terreneiro | X1: Comisão / Terreneiro | Y1: Adm. E Manutenção / Terreneiro | Z1: Tributos / Terreneiro | AA1: Participação Líquida Terreneiro | AB1: Participação de Sócios Minoritários (paga obra) | AC1: Area Total m2 | AD1: Data de Inicio de Construção | AE1: Custo Total do Terreno (Pré Rateio - R$mm) | AF1: Custo Total do Terreno (% do VGV) | AG1: Custo de Construção (Pré Rateio - R$mm) | AH1: Valor m2 Obra | AI1: m2 por Unidade | AJ1: Total de Unidades | AK1: Valor m2 Venda | AL1: VGV Total (R$mm) | AM1: VGV Total (R$mm) BT | AN1: Valor médio por terreno | AO1: Custo médio por terreno | AP1: % Paga obra | AQ1: Margem
A2: MAP001 | B2: CIDADE JARDIM - ETP I - BELA VISTA | C2: https://earth.google.com/web/search/BELA+VISTA/@-16.96124568,-48.94579579,823.03102905a,3707.10942264d,35y,-0h,0t,0r/data=CnkaSxJFCiUweDkzNWYyNTZjZmU4NDk4OGQ6MHhiNDk0MzE3NTE3MDU3YTA5GVl5E43_-DDAIcOVWL7TeUjAKgpCRUxBIFZJU1RBGAIgASImCiQJ0WMLs4K1IMAREBK2sOjBIMAZM_Z2zLqhSMAh4pu9YBioSMBCAggBOgMKATBCAggASggIl-fxrwUQAA?authuser=0 | D2: 1 | E2: LandBank | G2: 2040 | J2: 355 | K2: CENTRO-OESTE I | L2: BELA VISTA DE GOIÁS | M2: GO | N2: CIDADE JARDIM - ETP I | O2: Arrematação judicial | P2: 11775750 | Q2: Loteamento | R2: Sim | S2: 2026 | T2: 46203 | U2: 0.75 | V2: 0.25 | W2: =SUM(U2:V2) -> 1 | X2: 0.05 | Y2: 0.09 | Z2: 0.068 | AA2: 0.198 | AC2: =AI2*AJ2 -> 222798.36 | AE2: =P2/10^6 -> 11.77575 | AF2: =IF(AL2=0,0,AE2/AL2) -> 0.10786499 | AG2: =(AH2*AI2*AJ2)/10^6 -> 32.974158 | AH2: 148 | AI2: 305.20324 | AJ2: 730 | AK2: 490 | AL2: =(AK2*AJ2*AI2)/10^6 -> 109.1712 | AM2: =AL2*U2 -> 81.878399 | AN2: 149549.59 | AO2: =AH2*AI2 -> 45170.079 | AP2: =U2+AB2 -> 0.75 | AQ2: =AL2*AP2/(AG2+AE2) -> 1.8296887
A3: MAP001 | B3: CIDADE JARDIM - ETP II - BELA VISTA | C3: https://earth.google.com/web/search/BELA+VISTA/@-16.96124568,-48.94579579,823.03102905a,3707.10942264d,35y,-0h,0t,0r/data=CnkaSxJFCiUweDkzNWYyNTZjZmU4NDk4OGQ6MHhiNDk0MzE3NTE3MDU3YTA5GVl5E43_-DDAIcOVWL7TeUjAKgpCRUxBIFZJU1RBGAIgASImCiQJ0WMLs4K1IMAREBK2sOjBIMAZM_Z2zLqhSMAh4pu9YBioSMBCAggBOgMKATBCAggASggIl-fxrwUQAA?authuser=0 | D3: 1 | E3: LandBank | G3: 2040 | J3: 356 | K3: CENTRO-OESTE I | L3: BELA VISTA DE GOIÁS | M3: GO | N3: CIDADE JARDIM - ETP II | O3: Arrematação judicial | P3: 11775750 | Q3: Loteamento | R3: Sim | S3: 2028 | T3: 46934 | U3: 0.75 | V3: 0.25 | W3: =SUM(U3:V3) -> 1 | X3: 0.05 | Y3: 0.09 | Z3: 0.068 | AA3: 0.198 | AC3: =AI3*AJ3 -> 222798.36 | AE3: =P3/10^6 -> 11.77575 | AF3: =IF(AL3=0,0,AE3/AL3) -> 0.10786499 | AG3: =(AH3*AI3*AJ3)/10^6 -> 32.974158 | AH3: 148 | AI3: 304.78573 | AJ3: 731 | AK3: 490 | AL3: =(AK3*AJ3*AI3)/10^6 -> 109.1712 | AM3: =AL3*U3 -> 81.878399 | AN3: 149345.01 | AO3: =AH3*AI3 -> 45108.287 | AP3: =U3+AB3 -> 0.75 | AQ3: =AL3*AP3/(AG3+AE3) -> 1.8296887
A4: MAP122 | B4: JARDIM DO CERRADO 5 - GOIÂNIA | C4: https://earth.google.com/web/search/GOI%c3%82NIA/@-16.67746594,-49.42770992,858.01737984a,4789.30417081d,35y,9.31126662h,0.18897674t,360r/data=CiwiJgokCTImrsNH8yrAEajobj-t-irAGWOHbhWxkEjAIXn8jCOOlEjAQgIIAToDCgEwQgIIAEoICJfn8a8FEAA?authuser=0 | D4: 1 | E4: LandBank | G4: 2770 | J4: 358 | K4: CENTRO-OESTE II | L4: GOIÂNIA | M4: GO | N4: JARDIM DO CERRADO 5 | O4: Parceria | P4: 0 | Q4: Loteamento | R4: - | S4: 2030 | T4: 47848 | U4: 0.8 | W4: =SUM(U4:V4) -> 0.8 | AA4: 0.198 | AB4: 0.2 | AC4: =AI4*AJ4 -> 260020.4 | AE4: =P4/10^6 -> 0 | AF4: =IF(AL4=0,0,AE4/AL4) -> 0 | AG4: =(AH4*AI4*AJ4)/10^6 -> 38.483019 | AH4: 148 | AI4: 296.82694 | AJ4: 876 | AK4: 500 | AL4: =(AK4*AJ4*AI4)/10^6 -> 130.0102 | AM4: =AL4*U4 -> 104.00816 | AN4: 148413.47 | AO4: =AH4*AI4 -> 43930.387 | AP4: =U4+AB4 -> 1 | AQ4: =AL4*AP4/(AG4+AE4) -> 3.3783784
A5: MAP122 | B5: JARDIM DO CERRADO 6 - GOIÂNIA | C5: https://earth.google.com/web/search/GOI%c3%82NIA/@-16.67746594,-49.42770992,858.01737984a,4789.30417081d,35y,9.31126662h,0.18897674t,360r/data=CiwiJgokCTImrsNH8yrAEajobj-t-irAGWOHbhWxkEjAIXn8jCOOlEjAQgIIAToDCgEwQgIIAEoICJfn8a8FEAA?authuser=0 | D5: 1 | E5: LandBank | G5: 2770 | J5: 359 | K5: CENTRO-OESTE II | L5: GOIÂNIA | M5: GO | N5: JARDIM DO CERRADO 6 | O5: Parceria | P5: 0 | Q5: Loteamento | R5: - | S5: 2029 | T5: 47483 | U5: 0.8 | W5: =SUM(U5:V5) -> 0.8 | AA5: 0.198 | AB5: 0.2 | AC5: =AI5*AJ5 -> 134090.93 | AE5: =P5/10^6 -> 0 | AF5: =IF(AL5=0,0,AE5/AL5) -> 0 | AG5: =(AH5*AI5*AJ5)/10^6 -> 19.845458 | AH5: 148 | AI5: 292.1371 | AJ5: 459 | AK5: 500 | AL5: =(AK5*AJ5*AI5)/10^6 -> 67.045465 | AM5: =AL5*U5 -> 53.636372 | AN5: 146068.55 | AO5: =AH5*AI5 -> 43236.291 | AP5: =U5+AB5 -> 1 | AQ5: =AL5*AP5/(AG5+AE5) -> 3.3783784
A6: MAP122 | B6: JARDIM DO CERRADO 7 - GOIÂNIA | C6: https://earth.google.com/web/search/GOI%c3%82NIA/@-16.67746594,-49.42770992,858.01737984a,4789.30417081d,35y,9.31126662h,0.18897674t,360r/data=CiwiJgokCTImrsNH8yrAEajobj-t-irAGWOHbhWxkEjAIXn8jCOOlEjAQgIIAToDCgEwQgIIAEoICJfn8a8FEAA?authuser=0 | D6: 1 | E6: LandBank | G6: 2770 | J6: 360 | K6: CENTRO-OESTE II | L6: GOIÂNIA | M6: GO | N6: JARDIM DO CERRADO 7 | O6: Parceria | P6: 0 | Q6: Loteamento | R6: - | S6: 2026 | T6: 46295 | U6: 0.8 | W6: =SUM(U6:V6) -> 0.8 | AA6: 0.198 | AB6: 0.2 | AC6: =AI6*AJ6 -> 72284.41 | AE6: =P6/10^6 -> 0 | AF6: =IF(AL6=0,0,AE6/AL6) -> 0 | AG6: =(AH6*AI6*AJ6)/10^6 -> 10.698093 | AH6: 148 | AI6: 384.49154 | AJ6: 188 | AK6: 500 | AL6: =(AK6*AJ6*AI6)/10^6 -> 36.142205 | AM6: =AL6*U6 -> 28.913764 | AN6: 192245.77 | AO6: =AH6*AI6 -> 56904.748 | AP6: =U6+AB6 -> 1 | AQ6: =AL6*AP6/(AG6+AE6) -> 3.3783784
A7: MAP122 | B7: JARDIM DO CERRADO 8 - GOIÂNIA | C7: https://earth.google.com/web/search/GOI%c3%82NIA/@-16.67746594,-49.42770992,858.01737984a,4789.30417081d,35y,9.31126662h,0.18897674t,360r/data=CiwiJgokCTImrsNH8yrAEajobj-t-irAGWOHbhWxkEjAIXn8jCOOlEjAQgIIAToDCgEwQgIIAEoICJfn8a8FEAA?authuser=0 | D7: 1 | E7: LandBank | G7: 2770 | J7: 361 | K7: CENTRO-OESTE II | L7: GOIÂNIA | M7: GO | N7: JARDIM DO CERRADO 8 | O7: Parceria | P7: 0 | Q7: Loteamento | R7: - | S7: 2026 | T7: 46295 | U7: 0.8 | W7: =SUM(U7:V7) -> 0.8 | AA7: 0.198 | AB7: 0.2 | AC7: =AI7*AJ7 -> 78369.024 | AE7: =P7/10^6 -> 0 | AF7: =IF(AL7=0,0,AE7/AL7) -> 0 | AG7: =(AH7*AI7*AJ7)/10^6 -> 11.598615 | AH7: 148 | AI7: 279.88937 | AJ7: 280 | AK7: 500 | AL7: =(AK7*AJ7*AI7)/10^6 -> 39.184512 | AM7: =AL7*U7 -> 31.347609 | AN7: 139944.68 | AO7: =AH7*AI7 -> 41423.627 | AP7: =U7+AB7 -> 1 | AQ7: =AL7*AP7/(AG7+AE7) -> 3.3783784
A8: MAP122 | B8: JARDIM DO CERRADO 8 II - GOIÂNIA | C8: https://earth.google.com/web/search/GOI%c3%82NIA/@-16.67746594,-49.42770992,858.01737984a,4789.30417081d,35y,9.31126662h,0.18897674t,360r/data=CiwiJgokCTImrsNH8yrAEajobj-t-irAGWOHbhWxkEjAIXn8jCOOlEjAQgIIAToDCgEwQgIIAEoICJfn8a8FEAA?authuser=0 | D8: 1 | E8: LandBank | G8: 2770 | J8: 362 | K8: CENTRO-OESTE II | L8: GOIÂNIA | M8: GO | N8: JARDIM DO CERRADO 8 II | O8: Parceria | P8: 0 | Q8: Loteamento | R8: - | S8: 2028 | T8: 47118 | U8: 0.8 | W8: =SUM(U8:V8) -> 0.8 | AA8: 0.198 | AB8: 0.2 | AC8: =AI8*AJ8 -> 183607.43 | AE8: =P8/10^6 -> 0 | AF8: =IF(AL8=0,0,AE8/AL8) -> 0 | AG8: =(AH8*AI8*AJ8)/10^6 -> 27.173899 | AH8: 148 | AI8: 279.88937 | AJ8: 656 | AK8: 500 | AL8: =(AK8*AJ8*AI8)/10^6 -> 91.803713 | AM8: =AL8*U8 -> 73.442971 | AN8: 139944.68 | AO8: =AH8*AI8 -> 41423.627 | AP8: =U8+AB8 -> 1 | AQ8: =AL8*AP8/(AG8+AE8) -> 3.3783784
A9: MAP122 | B9: JARDIM DO CERRADO 9 - GOIÂNIA | C9: https://earth.google.com/web/search/GOI%c3%82NIA/@-16.67746594,-49.42770992,858.01737984a,4789.30417081d,35y,9.31126662h,0.18897674t,360r/data=CiwiJgokCTImrsNH8yrAEajobj-t-irAGWOHbhWxkEjAIXn8jCOOlEjAQgIIAToDCgEwQgIIAEoICJfn8a8FEAA?authuser=0 | D9: 1 | E9: LandBank | G9: 2770 | J9: 363 | K9: CENTRO-OESTE II | L9: GOIÂNIA | M9: GO | N9: JARDIM DO CERRADO 9 | O9: Parceria | P9: 0 | Q9: Loteamento | R9: - | S9: 2026 | T9: 46387 | U9: 0.8 | W9: =SUM(U9:V9) -> 0.8 | AA9: 0.198 | AB9: 0.2 | AC9: =AI9*AJ9 -> 132666.99 | AE9: =P9/10^6 -> 0 | AF9: =IF(AL9=0,0,AE9/AL9) -> 0 | AG9: =(AH9*AI9*AJ9)/10^6 -> 19.634715 | AH9: 148 | AI9: 282.87205 | AJ9: 469 | AK9: 500 | AL9: =(AK9*AJ9*AI9)/10^6 -> 66.333495 | AM9: =AL9*U9 -> 53.066796 | AN9: 141436.02 | AO9: =AH9*AI9 -> 41865.063 | AP9: =U9+AB9 -> 1 | AQ9: =AL9*AP9/(AG9+AE9) -> 3.3783784
A10: MAP122 | B10: JARDIM DO CERRADO 10 - GOIÂNIA | C10: https://earth.google.com/web/search/GOI%c3%82NIA/@-16.67746594,-49.42770992,858.01737984a,4789.30417081d,35y,9.31126662h,0.18897674t,360r/data=CiwiJgokCTImrsNH8yrAEajobj-t-irAGWOHbhWxkEjAIXn8jCOOlEjAQgIIAToDCgEwQgIIAEoICJfn8a8FEAA?authuser=0 | D10: 1 | E10: LandBank | G10: 2770 | J10: 364 | K10: CENTRO-OESTE II | L10: GOIÂNIA | M10: GO | N10: JARDIM DO CERRADO 10 | O10: Parceria | P10: 0 | Q10: Loteamento | R10: - | S10: 2027 | T10: 46752 | U10: 0.8 | W10: =SUM(U10:V10) -> 0.8 | AA10: 0.198 | AB10: 0.2 | AC10: =AI10*AJ10 -> 177762.71 | AE10: =P10/10^6 -> 0 | AF10: =IF(AL10=0,0,AE10/AL10) -> 0 | AG10: =(AH10*AI10*AJ10)/10^6 -> 26.308881 | AH10: 148 | AI10: 428.34388 | AJ10: 415 | AK10: 500 | AL10: =(AK10*AJ10*AI10)/10^6 -> 88.881355 | AM10: =AL10*U10 -> 71.105084 | AN10: 214171.94 | AO10: =AH10*AI10 -> 63394.894 | AP10: =U10+AB10 -> 1 | AQ10: =AL10*AP10/(AG10+AE10) -> 3.3783784
A11: MAP122 | B11: JARDIM DO CERRADO 11 - GOIÂNIA | C11: https://earth.google.com/web/search/GOI%c3%82NIA/@-16.67746594,-49.42770992,858.01737984a,4789.30417081d,35y,9.31126662h,0.18897674t,360r/data=CiwiJgokCTImrsNH8yrAEajobj-t-irAGWOHbhWxkEjAIXn8jCOOlEjAQgIIAToDCgEwQgIIAEoICJfn8a8FEAA?authuser=0 | D11: 1 | E11: LandBank | G11: 2770 | J11: 365 | K11: CENTRO-OESTE II | L11: GOIÂNIA | M11: GO | N11: JARDIM DO CERRADO 11 | O11: Parceria | P11: 0 | Q11: Loteamento | R11: - | S11: 2029 | T11: 47483 | U11: 0.8 | W11: =SUM(U11:V11) -> 0.8 | AA11: 0.198 | AB11: 0.2 | AC11: =AI11*AJ11 -> 51071.98 | AE11: =P11/10^6 -> 0 | AF11: =IF(AL11=0,0,AE11/AL11) -> 0 | AG11: =(AH11*AI11*AJ11)/10^6 -> 7.558653 | AH11: 148 | AI11: 263.25763 | AJ11: 194 | AK11: 500 | AL11: =(AK11*AJ11*AI11)/10^6 -> 25.53599 | AM11: =AL11*U11 -> 20.428792 | AN11: 131628.81 | AO11: =AH11*AI11 -> 38962.129 | AP11: =U11+AB11 -> 1 | AQ11: =AL11*AP11/(AG11+AE11) -> 3.3783784
A12: MAP125 | B12: RESIDENCIAL PAINEIRAS | D12: 1 | E12: LandBank | G12: 2177 | K12: CENTRO-OESTE II | L12: PORTO VELHO | M12: RO | N12: RESIDENCIAL PAINEIRAS | O12: Parceria | P12: 0 | Q12: Loteamento | R12: Sim | U12: 0.8 | W12: =SUM(U12:V12) -> 0.8 | AA12: 0.198 | AB12: 0.2 | AC12: =AI12*AJ12 -> 363235.45 | AE12: =P12/10^6 -> 0 | AF12: =IF(AL12=0,0,AE12/AL12) -> 0 | AG12: =(AH12*AI12*AJ12)/10^6 -> 48.346638 | AH12: 133.1 | AI12: 215.57 | AJ12: 1685 | AK12: 380 | AL12: =(AK12*AJ12*AI12)/10^6 -> 138.02947 | AM12: =AL12*U12 -> 110.42358 | AN12: 114000 | AO12: =AH12*AI12 -> 28692.367 | AP12: =U12+AB12 -> 1 | AQ12: =AL12*AP12/(AG12+AE12) -> 2.8549962
A13: MAP133 | B13: ANAMARIA SANTOS GUIMARÃES | D13: 1 | E13: LandBank | G13: 2041 | K13: CENTRO-OESTE II | L13: CALDAS NOVAS | M13: GO | N13: A DEFINIR | O13: Parceria | P13: 0 | Q13: Loteamento | U13: 0.725 | V13: =27.5%-15% -> 0.125 | W13: =SUM(U13:V13) -> 0.85 | AA13: 0.198 | AB13: 0.15 | AC13: 1669.242 | AE13: =P13/10^6 -> 0 | AF13: =IF(AL13=0,0,AE13/AL13) -> 0 | AG13: =(AH13*AI13*AJ13)/10^6 -> 196.54908 | AH13: 240 | AI13: 219.5 | AJ13: 3731 | AK13: 520 | AL13: =(AK13*AJ13*AI13)/10^6 -> 425.85634 | AM13: =AL13*U13 -> 308.74585 | AN13: 114140 | AO13: =AH13*AI13 -> 52680 | AP13: =U13+AB13 -> 0.875 | AQ13: =AL13*AP13/(AG13+AE13) -> 1.8958333
A14: MAP032 | B14: RESIDENCIAL ALTO DAS BARAUNAS II - ARAPIRACA | C14: https://earth.google.com/web/search/ARAPIRACA/@-9.74896182,-36.69647245,245.55478327a,4738.09539736d,35y,0h,0t,0r/data=CiwiJgokCclCL3e0IS_AESFNk5j5MS_AGZRIeMyvpUfAIcPoSk9ErkfAQgIIAToDCgEwQgIIAEoICJfn8a8FEAA?authuser=0 | D14: 1 | E14: LandBank | G14: 2045 | J14: 194 | K14: NORDESTE I | L14: ARAPIRACA | M14: AL | N14: RESIDENCIAL ALTO DAS BARAUNAS II | O14: Parceria | P14: 0 | Q14: Loteamento | R14: - | S14: 2027 | T14: 46568 | U14: 0.5304 | V14: 0.337 | W14: =SUM(U14:V14) -> 0.8674 | X14: 0.05 | Y14: 0.09 | Z14: 0.068 | AA14: 0.198 | AB14: 0.1326 | AC14: =AI14*AJ14 -> 169253.49 | AE14: =P14/10^6 -> 0 | AF14: =IF(AL14=0,0,AE14/AL14) -> 0 | AG14: =(AH14*AI14*AJ14)/10^6 -> 20.310419 | AH14: 120 | AI14: 187.64245 | AJ14: 902 | AK14: 426.10642 | AL14: =(AK14*AJ14*AI14)/10^6 -> 72.12 | AM14: =AL14*U14 -> 38.252448 | AN14: 79955.654 | AO14: =AH14*AI14 -> 22517.094 | AP14: =U14+AB14 -> 0.663 | AQ14: =AL14*AP14/(AG14+AE14) -> 2.354238
A15: MAP032 | B15: RESIDENCIAL ALTO DAS BARAUNAS II - SPT2 - ARAPIRACA | C15: https://earth.google.com/web/search/ARAPIRACA/@-9.74896182,-36.69647245,245.55478327a,4738.09539736d,35y,0h,0t,0r/data=CiwiJgokCclCL3e0IS_AESFNk5j5MS_AGZRIeMyvpUfAIcPoSk9ErkfAQgIIAToDCgEwQgIIAEoICJfn8a8FEAA?authuser=0 | D15: 1 | E15: LandBank | G15: 2045 | J15: 195 | K15: NORDESTE I | L15: ARAPIRACA | M15: AL | N15: RESIDENCIAL ALTO DAS BARAUNAS II - SPT2 | O15: Parceria | P15: 0 | Q15: Loteamento | R15: - | S15: 2028 | T15: 46934 | U15: 0.5304 | V15: 0.337 | W15: =SUM(U15:V15) -> 0.8674 | X15: 0.05 | Y15: 0.09 | Z15: 0.068 | AA15: 0.198 | AB15: 0.1326 | AC15: =AI15*AJ15 -> 169253.49 | AE15: =P15/10^6 -> 0 | AF15: =IF(AL15=0,0,AE15/AL15) -> 0 | AG15: =(AH15*AI15*AJ15)/10^6 -> 20.310419 | AH15: 120 | AI15: 187.85071 | AJ15: 901 | AK15: 426.10642 | AL15: =(AK15*AJ15*AI15)/10^6 -> 72.12 | AM15: =AL15*U15 -> 38.252448 | AN15: 80044.395 | AO15: =AH15*AI15 -> 22542.086 | AP15: =U15+AB15 -> 0.663 | AQ15: =AL15*AP15/(AG15+AE15) -> 2.354238
A16: MAP033 | B16: BURITI GARDEN PRIME - MARECHAL DEODORO | C16: https://earth.google.com/web/search/MARECHAL+DEODORO/@-9.75268373,-35.84765408,4.2701174a,3214.95034437d,35y,0h,0t,0r/data=CiwiJgokCWeqOyo7eCPAETh3cFu0hiPAGVxp7S1rVULAIVnrvdbgXELAQgIIAToDCgEwQgIIAEoICJfn8a8FEAA?authuser=0 | D16: 1 | E16: LandBank | G16: 2047 | J16: 196 | K16: NORDESTE I | L16: MARECHAL DEODORO | M16: AL | N16: BURITI GARDEN PRIME | O16: Parceria | P16: 0 | Q16: Condominio | R16: Sim | S16: 2026 | T16: 46203 | U16: 0.5086 | V16: 0.3642 | W16: =SUM(U16:V16) -> 0.8728 | X16: 0.05 | Y16: 0.09 | Z16: 0.068 | AA16: 0.198 | AB16: 0.1272 | AC16: =AI16*AJ16 -> 164975.96 | AE16: =P16/10^6 -> 0 | AF16: =IF(AL16=0,0,AE16/AL16) -> 0 | AG16: =(AH16*AI16*AJ16)/10^6 -> 42.89375 | AH16: 260 | AI16: 246.97 | AJ16: 668 | AK16: 949.68418 | AL16: =(AK16*AJ16*AI16)/10^6 -> 156.67506 | AM16: =AL16*U16 -> 79.684935 | AN16: 260000 | AO16: =AH16*AI16 -> 64212.2 | AP16: =U16+AB16 -> 0.6358 | AQ16: =AL16*AP16/(AG16+AE16) -> 2.3223431
A17: MAP034 | B17: RESIDENCIAL CIDADE JARDIM III - RIO LARGO | C17: https://earth.google.com/web/search/RIO+LARGO/@-9.52900304,-35.81653115,112.35298923a,4987.59724811d,35y,0.00000121h,0t,0r/data=CiwiJgokCbfopBmzfCPAEeMgyVIMhiPAGTrKKDMX6kHAIcF9G6ro7kHAQgIIAToDCgEwQgIIAEoICJfn8a8FEAA?authuser=0 | D17: 1 | E17: LandBank | G17: 2049 | J17: 197 | K17: NORDESTE I | L17: RIO LARGO | M17: AL | N17: RESIDENCIAL CIDADE JARDIM III | O17: Compra e Venda | P17: 1923793.1 | Q17: Loteamento | R17: Sim | S17: 2026 | T17: 46203 | U17: 0.8 | W17: =SUM(U17:V17) -> 0.8 | AA17: 0.198 | AB17: 0.2 | AC17: =AI17*AJ17 -> 247500 | AE17: =P17/10^6 -> 1.9237931 | AF17: =IF(AL17=0,0,AE17/AL17) -> 0.016446441 | AG17: =(AH17*AI17*AJ17)/10^6 -> 29.7 | AH17: 120 | AI17: 165 | AJ17: 1500 | AK17: 472.61904 | AL17: =(AK17*AJ17*AI17)/10^6 -> 116.97321 | AM17: =AL17*U17 -> 93.57857 | AN17: 79872.618 | AO17: =AH17*AI17 -> 19800 | AP17: =U17+AB17 -> 1 | AQ17: =AL17*AP17/(AG17+AE17) -> 3.6988989
A18: MAP034 | B18: RESIDENCIAL CIDADE JARDIM III - STP 2 - RIO LARGO | C18: https://earth.google.com/web/search/RIO+LARGO/@-9.52900304,-35.81653115,112.35298923a,4987.59724811d,35y,0.00000121h,0t,0r/data=CiwiJgokCbfopBmzfCPAEeMgyVIMhiPAGTrKKDMX6kHAIcF9G6ro7kHAQgIIAToDCgEwQgIIAEoICJfn8a8FEAA?authuser=0 | D18: 1 | E18: LandBank | G18: 2049 | J18: 198 | K18: NORDESTE I | L18: RIO LARGO | M18: AL | N18: RESIDENCIAL CIDADE JARDIM III - STP 2 | O18: Compra e Venda | P18: 1923792 | Q18: Loteamento | R18: Sim | S18: 2027 | T18: 46477 | U18: 0.8 | W18: =SUM(U18:V18) -> 0.8 | AA18: 0.198 | AB18: 0.2 | AC18: =AI18*AJ18 -> 165000 | AE18: =P18/10^6 -> 1.923792 | AF18: =IF(AL18=0,0,AE18/AL18) -> 0.024669648 | AG18: =(AH18*AI18*AJ18)/10^6 -> 19.8 | AH18: 120 | AI18: 165 | AJ18: 1000 | AK18: 472.61904 | AL18: =(AK18*AJ18*AI18)/10^6 -> 77.982142 | AM18: =AL18*U18 -> 62.385714 | AN18: 79872.618 | AO18: =AH18*AI18 -> 19800 | AP18: =U18+AB18 -> 1 | AQ18: =AL18*AP18/(AG18+AE18) -> 3.5897113
A19: MAP034 | B19: RESIDENCIAL CIDADE JARDIM III - STP 3 - RIO LARGO | C19: https://earth.google.com/web/search/RIO+LARGO/@-9.52900304,-35.81653115,112.35298923a,4987.59724811d,35y,0.00000121h,0t,0r/data=CiwiJgokCbfopBmzfCPAEeMgyVIMhiPAGTrKKDMX6kHAIcF9G6ro7kHAQgIIAToDCgEwQgIIAEoICJfn8a8FEAA?authuser=0 | D19: 1 | E19: LandBank | G19: 2049 | J19: 199 | K19: NORDESTE I | L19: RIO LARGO | M19: AL | N19: RESIDENCIAL CIDADE JARDIM III - STP 3 | O19: Compra e Venda | P19: 1923792 | Q19: Loteamento | R19: Sim | S19: 2028 | T19: 46934 | U19: 0.8 | W19: =SUM(U19:V19) -> 0.8 | AA19: 0.198 | AB19: 0.2 | AC19: =AI19*AJ19 -> 114840 | AE19: =P19/10^6 -> 1.923792 | AF19: =IF(AL19=0,0,AE19/AL19) -> 0.035444897 | AG19: =(AH19*AI19*AJ19)/10^6 -> 13.7808 | AH19: 120 | AI19: 165 | AJ19: 696 | AK19: 472.61904 | AL19: =(AK19*AJ19*AI19)/10^6 -> 54.275571 | AM19: =AL19*U19 -> 43.420457 | AN19: 79872.618 | AO19: =AH19*AI19 -> 19800 | AP19: =U19+AB19 -> 1 | AQ19: =AL19*AP19/(AG19+AE19) -> 3.4560319
A20: MAP035 | B20: RESIDENCIAL JARDIM AMERICA II - PENEDO | C20: https://earth.google.com/web/search/Penedo,+AL/@-10.25735808,-36.57115779,78.36658822a,3198.69005319d,35y,0h,0t,0r/data=CiwiJgokCSEY7vitZSLAEUE54MEYuCPAGb-vF-6sm0HAIR2ubXgmSkLAQgIIAToDCgEwQgIIAEoICJfn8a8FEAA?authuser=0 | D20: 1 | E20: LandBank | G20: 2048 | J20: 200 | K20: NORDESTE I | L20: PENEDO | M20: AL | N20: RESIDENCIAL JARDIM AMERICA II | O20: Compra e Venda | P20: 4000000 | Q20: Loteamento | R20: Sim | S20: 2026 | T20: 46203 | U20: 0.8 | W20: =SUM(U20:V20) -> 0.8 | AA20: 0.198 | AB20: 0.2 | AC20: =AI20*AJ20 -> 117415.64 | AE20: =P20/10^6 -> 4 | AF20: =IF(AL20=0,0,AE20/AL20) -> 0.079225609 | AG20: =(AH20*AI20*AJ20)/10^6 -> 14.089877 | AH20: 120 | AI20: 207.81529 | AJ20: 565 | AK20: 430 | AL20: =(AK20*AJ20*AI20)/10^6 -> 50.488725 | AM20: =AL20*U20 -> 40.39098 | AN20: 89360.576 | AO20: =AH20*AI20 -> 24937.835 | AP20: =U20+AB20 -> 1 | AQ20: =AL20*AP20/(AG20+AE20) -> 2.7909933
A21: MAP036 | B21: RESIDENCIAL JARDIM EUROPA 2 - ALAGOINHA | C21: https://earth.google.com/web/search/RESIDENCIAL+JARDIM+EUROPA+2+-+ALAGOINHA/@-12.16901753,-38.4079717,117.33325024a,3592.41516492d,35y,0h,0t,0r/data=CiwiJgokCVvsaFFQZxrAESI5vVrxVB7AGWgJCTaDWkHAIWhUtp4sXELAQgIIAToDCgEwQgIIAEoICJfn8a8FEAA?authuser=0 | D21: 1 | E21: LandBank | G21: 2044 | J21: 201 | K21: NORDESTE I | L21: ALAGOINHA | M21: PB | N21: RESIDENCIAL JARDIM EUROPA 2 | O21: Compra e Venda | P21: 2000000 | Q21: Loteamento | R21: Sim | S21: 2028 | T21: 46843 | U21: 0.8 | W21: =SUM(U21:V21) -> 0.8 | AA21: 0.198 | AB21: 0.2 | AC21: =AI21*AJ21 -> 187500 | AE21: =P21/10^6 -> 2 | AF21: =IF(AL21=0,0,AE21/AL21) -> 0.023188406 | AG21: =(AH21*AI21*AJ21)/10^6 -> 22.5 | AH21: 120 | AI21: 180 | AJ21: 1041.6667 | AK21: 460 | AL21: =(AK21*AJ21*AI21)/10^6 -> 86.25 | AM21: =AL21*U21 -> 69 | AN21: 82800 | AO21: =AH21*AI21 -> 21600 | AP21: =U21+AB21 -> 1 | AQ21: =AL21*AP21/(AG21+AE21) -> 3.5204082
A22: MAP037 | B22: RESIDENCIAL JARDIM EUROPA - BARRA DOS COQUEIROS | C22: https://earth.google.com/web/search/BARRA+DOS+COQUEIROS/@-10.86709266,-36.98473154,9.11625276a,6838.59037115d,35y,0h,0t,0r/data=CiwiJgokCez0LUwI4RzAEc6AbPlB_xzAGXUWKXAsqkPAIYL6q2XpsUPAQgIIAToDCgEwQgIIAEoICJfn8a8FEAA?authuser=0 | D22: 1 | E22: LandBank | G22: 2046 | J22: 202 | K22: NORDESTE I | L22: BARRA DOS COQUEIROS | M22: SE | N22: RESIDENCIAL JARDIM EUROPA | O22: Compra e Venda | P22: 4000000 | Q22: Loteamento | R22: - | S22: 2027 | T22: 46568 | U22: 0.8 | W22: =SUM(U22:V22) -> 0.8 | AA22: 0.198 | AB22: 0.2 | AC22: =AI22*AJ22 -> 204159.05 | AE22: =P22/10^6 -> 4 | AF22: =IF(AL22=0,0,AE22/AL22) -> 0.045564111 | AG22: =(AH22*AI22*AJ22)/10^6 -> 24.499086 | AH22: 120 | AI22: 216.27018 | AJ22: 944 | AK22: 430 | AL22: =(AK22*AJ22*AI22)/10^6 -> 87.788392 | AM22: =AL22*U22 -> 70.230713 | AN22: 92996.177 | AO22: =AH22*AI22 -> 25952.422 | AP22: =U22+AB22 -> 1 | AQ22: =AL22*AP22/(AG22+AE22) -> 3.0803932
A23: MAP037 | B23: RESIDENCIAL JARDIM EUROPA - BARRA DOS COQUEIROS | C23: https://earth.google.com/web/search/BARRA+DOS+COQUEIROS/@-10.86709266,-36.98473154,9.11625276a,6838.59037115d,35y,0h,0t,0r/data=CiwiJgokCez0LUwI4RzAEc6AbPlB_xzAGXUWKXAsqkPAIYL6q2XpsUPAQgIIAToDCgEwQgIIAEoICJfn8a8FEAA?authuser=0 | D23: 1 | E23: LandBank | G23: 2046 | J23: 203 | K23: NORDESTE I | L23: BARRA DOS COQUEIROS | M23: SE | N23: RESIDENCIAL JARDIM EUROPA | O23: Compra e Venda | P23: 4000000 | Q23: Loteamento | R23: - | S23: 2028 | T23: 46934 | U23: 0.8 | W23: =SUM(U23:V23) -> 0.8 | AA23: 0.198 | AB23: 0.2 | AC23: =AI23*AJ23 -> 204159.05 | AE23: =P23/10^6 -> 4 | AF23: =IF(AL23=0,0,AE23/AL23) -> 0.045564111 | AG23: =(AH23*AI23*AJ23)/10^6 -> 24.499086 | AH23: 120 | AI23: 216.49952 | AJ23: 943 | AK23: 430 | AL23: =(AK23*AJ23*AI23)/10^6 -> 87.788391 | AM23: =AL23*U23 -> 70.230713 | AN23: 93094.795 | AO23: =AH23*AI23 -> 25979.943 | AP23: =U23+AB23 -> 1 | AQ23: =AL23*AP23/(AG23+AE23) -> 3.0803932
A24: MAP038 | B24: JARDIM TROPICAL - CRATO | C24: https://earth.google.com/web/search/CRATO/@-7.23451766,-39.35968774,395.14410239a,4808.57124561d,35y,0h,0t,0r/data=CiwiJgokCREenKRkwgvAEaRMcJe6-AvAGbMRrrPsyUPAIf7hsFbW0EPAQgIIAToDCgEwQgIIAEoICJfn8a8FEAA?authuser=0 | D24: 1 | E24: LandBank | G24: 2053 | J24: 204 | K24: NORDESTE II | L24: CRATO | M24: CE | N24: JARDIM TROPICAL | O24: Compra e Venda | P24: 750000 | Q24: Loteamento | R24: Sim | S24: 2026 | T24: 46295 | U24: 0.725 | V24: 0.275 | W24: =SUM(U24:V24) -> 1 | X24: 0.05 | Y24: 0 | Z24: 0.068 | AA24: 0.198 | AC24: 187916 | AE24: =P24/10^6 -> 0.75 | AF24: =IF(AL24=0,0,AE24/AL24) -> 0.0066461787 | AG24: =(AH24*AI24*AJ24)/10^6 -> 22.56936 | AH24: 120 | AI24: 206 | AJ24: 913 | AK24: 600 | AL24: =(AK24*AJ24*AI24)/10^6 -> 112.8468 | AM24: =AL24*U24 -> 81.81393 | AN24: 108000 | AO24: =AH24*AI24 -> 24720 | AP24: =U24+AB24 -> 0.725 | AQ24: =AL24*AP24/(AG24+AE24) -> 3.5084123
A25: MAP039 | B25: JARDIM TROPICAL - ITAPIPOCA | C25: https://earth.google.com/web/search/ITAPIPOCA/@-3.48318447,-39.60453858,85.75014124a,4591.68380015d,35y,0h,0t,0r/data=CiwiJgokCSj18Ul83hfAEYrTwO0U8hfAGYnj-uRdJETAIcMsoPJeKUTAQgIIAToDCgEwQgIIAEoICJfn8a8FEAA?authuser=0 | D25: 1 | E25: LandBank | G25: 2054 | J25: 205 | K25: NORDESTE II | L25: ITAPIPOCA | M25: CE | N25: JARDIM TROPICAL | O25: Compra e Venda | P25: 750000 | Q25: Loteamento | R25: Sim | S25: 2026 | T25: 46295 | U25: 0.8 | V25: 0.2 | W25: =SUM(U25:V25) -> 1 | X25: 0.05 | Y25: 0 | Z25: 0.068 | AA25: 0.198 | AC25: 186731 | AE25: =P25/10^6 -> 0.75 | AF25: =IF(AL25=0,0,AE25/AL25) -> 0.0080479011 | AG25: =(AH25*AI25*AJ25)/10^6 -> 24.789072 | AH25: 133 | AI25: 176 | AJ25: 1059 | AK25: 500 | AL25: =(AK25*AJ25*AI25)/10^6 -> 93.192 | AM25: =AL25*U25 -> 74.5536 | AN25: 45000 | AO25: =AH25*AI25 -> 23408 | AP25: =U25+AB25 -> 0.8 | AQ25: =AL25*AP25/(AG25+AE25) -> 2.9191977
A26: MAP039 | B26: JARDIM TROPICAL II - ITAPIPOCA | C26: https://earth.google.com/web/search/ITAPIPOCA/@-3.48318447,-39.60453858,85.75014124a,4591.68380015d,35y,0h,0t,0r/data=CiwiJgokCSj18Ul83hfAEYrTwO0U8hfAGYnj-uRdJETAIcMsoPJeKUTAQgIIAToDCgEwQgIIAEoICJfn8a8FEAA?authuser=0 | D26: 1 | E26: LandBank | G26: 2054 | J26: 206 | K26: NORDESTE II | L26: ITAPIPOCA | M26: CE | N26: JARDIM TROPICAL II | O26: Compra e Venda | P26: 750000 | Q26: Loteamento | R26: Sim | S26: 2028 | T26: 47026 | U26: 0.8 | V26: 0.2 | W26: =SUM(U26:V26) -> 1 | X26: 0.05 | Y26: 0 | Z26: 0.068 | AA26: 0.198 | AC26: 186731 | AE26: =P26/10^6 -> 0.75 | AF26: =IF(AL26=0,0,AE26/AL26) -> 0.0080479011 | AG26: =(AH26*AI26*AJ26)/10^6 -> 24.789072 | AH26: 133 | AI26: 176 | AJ26: 1059 | AK26: 500 | AL26: =(AK26*AJ26*AI26)/10^6 -> 93.192 | AM26: =AL26*U26 -> 74.5536 | AN26: 45000 | AO26: =AH26*AI26 -> 23408 | AP26: =U26+AB26 -> 0.8 | AQ26: =AL26*AP26/(AG26+AE26) -> 2.9191977
A27: MAP040 | B27: JARDIM AMERICA II - TAUÁ | C27: https://earth.google.com/web/search/TAU%c3%81/@-5.97683983,-40.30366275,407.4430109a,2966.57752085d,35y,0h,0t,0r/data=CiwiJgokCVwuodN7uSdAEajZ7_kEaz3AGcctYEv-xi1AIcrxv7LiwVjAQgIIAToDCgEwQgIIAEoICJfn8a8FEAA?authuser=0 | D27: 1 | E27: LandBank | G27: 2056 | J27: 207 | K27: NORDESTE II | L27: TAUÁ | M27: CE | N27: JARDIM AMERICA II | O27: Parceria | P27: 0 | Q27: Loteamento | R27: Sim | S27: 2028 | T27: 46842 | U27: 0.79 | V27: 0.21 | W27: =SUM(U27:V27) -> 1 | X27: 0.05 | Y27: 0 | Z27: 0.068 | AA27: 0.198 | AC27: 201305 | AE27: =P27/10^6 -> 0 | AF27: =IF(AL27=0,0,AE27/AL27) -> 0 | AG27: =(AH27*AI27*AJ27)/10^6 -> 21.793536 | AH27: 108 | AI27: 192 | AJ27: 1051 | AK27: 480 | AL27: =(AK27*AJ27*AI27)/10^6 -> 96.86016 | AM27: =AL27*U27 -> 76.519526 | AN27: 43200 | AO27: =AH27*AI27 -> 20736 | AP27: =U27+AB27 -> 0.79 | AQ27: =AL27*AP27/(AG27+AE27) -> 3.5111111
A28: MAP040 | B28: JARDIM AMERICA III - TAUÁ | C28: https://earth.google.com/web/search/TAU%c3%81/@-5.97683983,-40.30366275,407.4430109a,2966.57752085d,35y,0h,0t,0r/data=CiwiJgokCVwuodN7uSdAEajZ7_kEaz3AGcctYEv-xi1AIcrxv7LiwVjAQgIIAToDCgEwQgIIAEoICJfn8a8FEAA?authuser=0 | D28: 1 | E28: LandBank | G28: 2056 | J28: 208 | K28: NORDESTE II | L28: TAUÁ | M28: CE | N28: JARDIM AMERICA III | O28: Parceria | P28: 0 | Q28: Loteamento | R28: Sim | S28: 2030 | T28: 47572 | U28: 0.79 | V28: 0.21 | W28: =SUM(U28:V28) -> 1 | X28: 0.05 | Y28: 0 | Z28: 0.068 | AA28: 0.198 | AC28: 201305 | AE28: =P28/10^6 -> 0 | AF28: =IF(AL28=0,0,AE28/AL28) -> 0 | AG28: =(AH28*AI28*AJ28)/10^6 -> 21.793536 | AH28: 108 | AI28: 192 | AJ28: 1051 | AK28: 480 | AL28: =(AK28*AJ28*AI28)/10^6 -> 96.86016 | AM28: =AL28*U28 -> 76.519526 | AN28: 43200 | AO28: =AH28*AI28 -> 20736 | AP28: =U28+AB28 -> 0.79 | AQ28: =AL28*AP28/(AG28+AE28) -> 3.5111111
A29: MAP041 | B29: RESIDENCIAL CIDADE JARDIM - BALSAS | C29: https://earth.google.com/web/search/BALSAS/@-7.55676262,-46.08364445,276.35723714a,5135.12989945d,35y,0h,0t,0r/data=CiwiJgokCeJxBz6CxDDAEQlwGFeXzDDAGfey9riu6UXAIWSXkF1C8kXAQgIIAToDCgEwQgIIAEoICJfn8a8FEAA?authuser=0 | D29: 1 | E29: LandBank | F29: REVER PROJETOS | G29: 2052 | J29: 209 | K29: NORDESTE II | L29: BALSAS | M29: MA | N29: RESIDENCIAL CIDADE JARDIM I - STP1 | O29: Parceria | P29: 0 | Q29: Loteamento | R29: Sim | S29: 2026 | T29: 46387 | U29: 0.8 | V29: 0.2 | W29: =SUM(U29:V29) -> 1 | X29: 0.05 | Y29: 0 | Z29: 0.068 | AA29: 0.198 | AC29: =AI29*AJ29 -> 306340 | AE29: =P29/10^6 -> 0 | AF29: =IF(AL29=0,0,AE29/AL29) -> 0 | AG29: =(AH29*AI29*AJ29)/10^6 -> 36.7608 | AH29: 120 | AI29: 265 | AJ29: 1156 | AK29: 500 | AL29: =(AK29*AJ29*AI29)/10^6 -> 153.17 | AM29: =AL29*U29 -> 122.536 | AN29: 132616.47 | AO29: =AH29*AI29 -> 31800 | AP29: =U29+AB29 -> 0.8 | AQ29: =AL29*AP29/(AG29+AE29) -> 3.3333333
A30: MAP041 | B30: RESIDENCIAL CIDADE JARDIM - SUBETAPA2 - BALSAS | C30: https://earth.google.com/web/search/BALSAS/@-7.55676262,-46.08364445,276.35723714a,5135.12989945d,35y,0h,0t,0r/data=CiwiJgokCeJxBz6CxDDAEQlwGFeXzDDAGfey9riu6UXAIWSXkF1C8kXAQgIIAToDCgEwQgIIAEoICJfn8a8FEAA?authuser=0 | D30: 1 | E30: LandBank | F30: REVER PROJETOS | G30: 2052 | J30: 210 | K30: NORDESTE II | L30: BALSAS | M30: MA | N30: RESIDENCIAL CIDADE JARDIM I - STP2 | O30: Parceria | P30: 0 | Q30: Loteamento | R30: Sim | S30: 2027 | T30: 46660 | U30: 0.8 | V30: 0.2 | W30: =SUM(U30:V30) -> 1 | X30: 0.05 | Y30: 0 | Z30: 0.068 | AA30: 0.198 | AC30: =AI30*AJ30 -> 306340 | AE30: =P30/10^6 -> 0 | AF30: =IF(AL30=0,0,AE30/AL30) -> 0 | AG30: =(AH30*AI30*AJ30)/10^6 -> 36.7608 | AH30: 120 | AI30: 265 | AJ30: 1156 | AK30: 500 | AL30: =(AK30*AJ30*AI30)/10^6 -> 153.17 | AM30: =AL30*U30 -> 122.536 | AN30: 132616.47 | AO30: =AH30*AI30 -> 31800 | AP30: =U30+AB30 -> 0.8 | AQ30: =AL30*AP30/(AG30+AE30) -> 3.3333333
A31: MAP042 | B31: RESIDENCIAL CIDADE JARDIM II - BALSAS | C31: https://earth.google.com/web/search/BALSAS/@-7.55676262,-46.08364445,276.35723714a,5135.12989945d,35y,0h,0t,0r/data=CiwiJgokCeJxBz6CxDDAEQlwGFeXzDDAGfey9riu6UXAIWSXkF1C8kXAQgIIAToDCgEwQgIIAEoICJfn8a8FEAA?authuser=0 | D31: 1 | E31: LandBank | F31: REVER PROJETOS | G31: 2052 | J31: 211 | K31: NORDESTE II | L31: BALSAS | M31: MA | N31: RESIDENCIAL CIDADE JARDIM II | O31: Parceria | P31: 0 | Q31: Loteamento | R31: - | S31: 2029 | T31: 47391 | U31: 0.8 | V31: 0.2 | W31: =SUM(U31:V31) -> 1 | X31: 0.05 | Y31: 0 | Z31: 0.068 | AA31: 0.198 | AC31: =AI31*AJ31 -> 271890 | AE31: =P31/10^6 -> 0 | AF31: =IF(AL31=0,0,AE31/AL31) -> 0 | AG31: =(AH31*AI31*AJ31)/10^6 -> 32.6268 | AH31: 120 | AI31: 265 | AJ31: 1026 | AK31: 500 | AL31: =(AK31*AJ31*AI31)/10^6 -> 135.945 | AM31: =AL31*U31 -> 108.756 | AN31: 124993.83 | AO31: =AH31*AI31 -> 31800 | AP31: =U31+AB31 -> 0.8 | AQ31: =AL31*AP31/(AG31+AE31) -> 3.3333333
A32: MAP042 | B32: RESIDENCIAL CIDADE JARDIM III - BALSAS | C32: https://earth.google.com/web/search/BALSAS/@-7.55676262,-46.08364445,276.35723714a,5135.12989945d,35y,0h,0t,0r/data=CiwiJgokCeJxBz6CxDDAEQlwGFeXzDDAGfey9riu6UXAIWSXkF1C8kXAQgIIAToDCgEwQgIIAEoICJfn8a8FEAA?authuser=0 | D32: 1 | E32: LandBank | F32: REVER PROJETOS | G32: 2052 | J32: 212 | K32: NORDESTE II | L32: BALSAS | M32: MA | N32: RESIDENCIAL CIDADE JARDIM III | O32: Parceria | P32: 0 | Q32: Loteamento | R32: - | S32: 2030 | T32: 48487 | U32: 0.8 | V32: 0.2 | W32: =SUM(U32:V32) -> 1 | X32: 0.05 | Y32: 0 | Z32: 0.068 | AA32: 0.198 | AC32: =AI32*AJ32 -> 271890 | AE32: =P32/10^6 -> 0 | AF32: =IF(AL32=0,0,AE32/AL32) -> 0 | AG32: =(AH32*AI32*AJ32)/10^6 -> 32.6268 | AH32: 120 | AI32: 265 | AJ32: 1026 | AK32: 500 | AL32: =(AK32*AJ32*AI32)/10^6 -> 135.945 | AM32: =AL32*U32 -> 108.756 | AN32: 124993.83 | AO32: =AH32*AI32 -> 31800 | AP32: =U32+AB32 -> 0.8 | AQ32: =AL32*AP32/(AG32+AE32) -> 3.3333333
A33: MAP002 | B33: A DEFINIR - ELDORADO DO CARAJAS | C33: https://earth.google.com/web/search/A+DEFINIR+-+ELDORADO+DO+CARAJAS/@-6.10130618,-49.38645125,132.08489807a,3593.41495385d,35y,0h,0t,0r/data=CiwiJgokCW1sITprhAPAEVxoH91ezwPAGZD9qRETXkvAIZjXKt-ZZ0vAQgIIAToDCgEwQgIIAEoICJfn8a8FEAA?authuser=0 | D33: Ativo | E33: LandBank | G33: 2119 | J33: 136 | K33: NORTE | L33: ELDORADO DO CARAJAS | M33: PA | N33: A DEFINIR | O33: Compra e Venda | P33: 84310 | Q33: Loteamento | R33: - | S33: - | T33: - | U33: 1 | W33: =SUM(U33:V33) -> 1 | AA33: 0.198 | AC33: =AI33*AJ33 -> 136646.78 | AE33: =P33/10^6 -> 0.08431 | AF33: =IF(AL33=0,0,AE33/AL33) -> 0.0022811147 | AG33: =(AH33*AI33*AJ33)/10^6 -> 10.931742 | AH33: 80 | AI33: 221.82919 | AJ33: 616 | AK33: 270.47838 | AL33: =(AK33*AJ33*AI33)/10^6 -> 36.96 | AM33: =AL33*U33 -> 36.96 | AN33: 60000 | AO33: =AH33*AI33 -> 17746.335 | AP33: =U33+AB33 -> 1 | AQ33: =AL33*AP33/(AG33+AE33) -> 3.3551039
A34: MAP003 | B34: CIDADE JARDIM III - PARAGOMINAS | C34: https://earth.google.com/web/search/CIDADE+JARDIM+III+-+PARAGOMINAS/@-2.98095416,-47.3799762,134.97977097a,3030.5675351d,34.99995839y,0h,0t,0r/data=CiwiJgokCSuOdv50fyPAET9A346_gyPAGQZ87NXc6kHAIQ521gYT7UHAQgIIAToDCgEwQgIIAEoICJfn8a8FEAA?authuser=0 | D34: 1 | E34: LandBank | G34: 2115 | H34: 4 | J34: 137 | K34: NORTE | L34: PARAGOMINAS | M34: PA | N34: CIDADE JARDIM III | O34: Compra e Venda | P34: 60000 | Q34: Loteamento | R34: Sim | S34: - | T34: - | U34: 1 | W34: =SUM(U34:V34) -> 1 | AA34: 0.198 | AC34: =AI34*AJ34 -> 11175.27 | AE34: =P34/10^6 -> 0.06 | AF34: =IF(AL34=0,0,AE34/AL34) -> 0.013953488 | AG34: =(AH34*AI34*AJ34)/10^6 -> 0.8940216 | AH34: 80 | AI34: 259.89 | AJ34: 43 | AK34: 384.77818 | AL34: =(AK34*AJ34*AI34)/10^6 -> 4.3 | AM34: =AL34*U34 -> 4.3 | AN34: 100000 | AO34: =AH34*AI34 -> 20791.2 | AP34: =U34+AB34 -> 1 | AQ34: =AL34*AP34/(AG34+AE34) -> 4.5072355
A35: MAP003 | B35: CIDADE JARDIM IV - PARAGOMINAS | C35: https://earth.google.com/web/search/CIDADE+JARDIM+III+-+PARAGOMINAS/@-2.98095416,-47.3799762,134.97977097a,3030.5675351d,34.99995839y,0h,0t,0r/data=CiwiJgokCSuOdv50fyPAET9A346_gyPAGQZ87NXc6kHAIQ521gYT7UHAQgIIAToDCgEwQgIIAEoICJfn8a8FEAA?authuser=0 | D35: 1 | E35: LandBank | G35: 2115 | H35: 4 | J35: 138 | K35: NORTE | L35: PARAGOMINAS | M35: PA | N35: CIDADE JARDIM IV | O35: Compra e Venda | P35: 60000 | Q35: Loteamento | R35: Sim | S35: - | T35: - | U35: 1 | W35: =SUM(U35:V35) -> 1 | AA35: 0.198 | AC35: =AI35*AJ35 -> 21556.5 | AE35: =P35/10^6 -> 0.06 | AF35: =IF(AL35=0,0,AE35/AL35) -> 0.0064935065 | AG35: =(AH35*AI35*AJ35)/10^6 -> 1.72452 | AH35: 80 | AI35: 279.95455 | AJ35: 77 | AK35: 428.64101 | AL35: =(AK35*AJ35*AI35)/10^6 -> 9.24 | AM35: =AL35*U35 -> 9.24 | AN35: 120000 | AO35: =AH35*AI35 -> 22396.364 | AP35: =U35+AB35 -> 1 | AQ35: =AL35*AP35/(AG35+AE35) -> 5.177863
A36: MAP006 | B36: DEFINIR - ÁREA SERRARIA CUMARU - REDENÇÃO | C36: https://earth.google.com/web/search/Reden%c3%a7%c3%a3o,+PA/@-8.02281704,-50.02474338,207.09019485a,9467.67478846d,35y,-0h,0t,0r/data=Cn0aTxJJCiUweDkyZTAwODAxOTFiMWU4Mzk6MHgzZDhmOGEwNDFiM2MxMGRkGS5nALkODyDAIUkmTL0TBEnAKg5SZWRlbsOnw6NvLCBQQRgCIAEiJgokCVbvBcmbxgfAEZZRXQph6wfAGYZHDZRMrkfAIcoEsIr5skfAQgIIAToDCgEwQgIIAEoICJfn8a8FEAA?authuser=0 | D36: 1 | E36: LandBank | G36: 2117 | J36: 145 | K36: NORTE | L36: REDENÇÃO | M36: PA | N36: A DEFINIR - ÁREA SERRARIA CUMARU | O36: Compra e Venda | P36: 2372312.5 | Q36: Loteamento | R36: - | S36: - | T36: - | U36: 1 | W36: =SUM(U36:V36) -> 1 | AA36: 0.198 | AC36: =AI36*AJ36 -> 43078.78 | AE36: =P36/10^6 -> 2.3723125 | AF36: =IF(AL36=0,0,AE36/AL36) -> 0.16474392 | AG36: =(AH36*AI36*AJ36)/10^6 -> 3.4463024 | AH36: 80 | AI36: 2393.2656 | AJ36: 18 | AK36: 334.2713 | AL36: =(AK36*AJ36*AI36)/10^6 -> 14.4 | AM36: =AL36*U36 -> 14.4 | AN36: 800000 | AO36: =AH36*AI36 -> 191461.24 | AP36: =U36+AB36 -> 1 | AQ36: =AL36*AP36/(AG36+AE36) -> 2.4748158
A37: MAP007 | B37: RESIDENCIAL BELA VISTA - REDENÇÃO | C37: https://earth.google.com/web/search/Reden%c3%a7%c3%a3o,+PA/@-8.02281704,-50.02474338,207.09019485a,9467.67478846d,35y,-0h,0t,0r/data=Cn0aTxJJCiUweDkyZTAwODAxOTFiMWU4Mzk6MHgzZDhmOGEwNDFiM2MxMGRkGS5nALkODyDAIUkmTL0TBEnAKg5SZWRlbsOnw6NvLCBQQRgCIAEiJgokCVbvBcmbxgfAEZZRXQph6wfAGYZHDZRMrkfAIcoEsIr5skfAQgIIAToDCgEwQgIIAEoICJfn8a8FEAA?authuser=0 | D37: 1 | E37: LandBank | G37: 2116 | J37: 146 | K37: NORTE | L37: REDENÇÃO | M37: PA | N37: RESIDENCIAL BELA VISTA | O37: Compra e Venda | P37: 2372312.5 | Q37: Loteamento | R37: - | S37: 2026 | T37: 46387 | U37: 0.99 | W37: =SUM(U37:V37) -> 0.99 | AA37: 0.198 | AB37: 0.01 | AC37: =AI37*AJ37 -> 130680 | AE37: =P37/10^6 -> 2.3723125 | AF37: =IF(AL37=0,0,AE37/AL37) -> 0.042217675 | AG37: =(AH37*AI37*AJ37)/10^6 -> 17.393508 | AH37: 133.1 | AI37: 220 | AJ37: 594 | AK37: 430 | AL37: =(AK37*AJ37*AI37)/10^6 -> 56.1924 | AM37: =AL37*U37 -> 55.630476 | AN37: 94600 | AO37: =AH37*AI37 -> 29282 | AP37: =U37+AB37 -> 1 | AQ37: =AL37*AP37/(AG37+AE37) -> 2.8429075
A38: MAP008 | B38: CIDADE JARDIM III - SUBETAPA 1 - SANTARÉM | C38: https://earth.google.com/web/search/CIDADE+JARDIM+12+-+PARAUAPEBAS/@-2.45795692,-54.77217012,46.50042218a,6405.178905d,35y,-0h,0t,0r/data=CiwiJgokCdmVqMeMyQbAESVW3mJaMwnAGYI6tUF7jUfAIaCAQToN3EfAQgIIAToDCgEwQgIIAEoICJfn8a8FEAA | D38: 1 | E38: LandBank | G38: 2121 | J38: 147 | K38: NORTE | L38: SANTARÉM | M38: PA | N38: CIDADE JARDIM III - SUBETAPA 1 | O38: Aquisição de Cotas | P38: 4800000 | Q38: Loteamento | R38: Sim | S38: 2026 | T38: 46387 | U38: 1 | W38: =SUM(U38:V38) -> 1 | AA38: 0.198 | AC38: =AI38*AJ38 -> 268937.01 | AE38: =P38/10^6 -> 4.8 | AF38: =IF(AL38=0,0,AE38/AL38) -> 0.027458532 | AG38: =(AH38*AI38*AJ38)/10^6 -> 35.795516 | AH38: 133.1 | AI38: 279.27 | AJ38: 963 | AK38: 650 | AL38: =(AK38*AJ38*AI38)/10^6 -> 174.80906 | AM38: =AL38*U38 -> 174.80906 | AN38: 168559.39 | AO38: =AH38*AI38 -> 37170.837 | AP38: =U38+AB38 -> 1 | AQ38: =AL38*AP38/(AG38+AE38) -> 4.3061174
A39: MAP008 | B39: CIDADE JARDIM III - SUBETAPA 2 - SANTARÉM | C39: https://earth.google.com/web/search/CIDADE+JARDIM+12+-+PARAUAPEBAS/@-2.45795692,-54.77217012,46.50042218a,6405.178905d,35y,-0h,0t,0r/data=CiwiJgokCdmVqMeMyQbAESVW3mJaMwnAGYI6tUF7jUfAIaCAQToN3EfAQgIIAToDCgEwQgIIAEoICJfn8a8FEAA | D39: 1 | E39: LandBank | G39: 2121 | J39: 148 | K39: NORTE | L39: SANTARÉM | M39: PA | N39: CIDADE JARDIM III - SUBETAPA 2 | O39: Aquisição de Cotas | P39: 4800000 | Q39: Loteamento | R39: Sim | S39: 2027 | T39: 46752 | U39: 1 | W39: =SUM(U39:V39) -> 1 | AA39: 0.198 | AC39: =AI39*AJ39 -> 269216.28 | AE39: =P39/10^6 -> 4.8 | AF39: =IF(AL39=0,0,AE39/AL39) -> 0.027430048 | AG39: =(AH39*AI39*AJ39)/10^6 -> 35.832687 | AH39: 133.1 | AI39: 279.27 | AJ39: 964 | AK39: 650 | AL39: =(AK39*AJ39*AI39)/10^6 -> 174.99058 | AM39: =AL39*U39 -> 174.99058 | AN39: 168559.39 | AO39: =AH39*AI39 -> 37170.837 | AP39: =U39+AB39 -> 1 | AQ39: =AL39*AP39/(AG39+AE39) -> 4.3066456
A40: MAP009 | B40: CIDADE JARDIM IV - SANTARÉM | C40: https://earth.google.com/web/search/CIDADE+JARDIM+12+-+PARAUAPEBAS/@-2.45795692,-54.77217012,46.50042218a,6405.178905d,35y,-0h,0t,0r/data=CiwiJgokCdmVqMeMyQbAESVW3mJaMwnAGYI6tUF7jUfAIaCAQToN3EfAQgIIAToDCgEwQgIIAEoICJfn8a8FEAA | D40: 1 | E40: LandBank | G40: 2121 | J40: 149 | K40: NORTE | L40: SANTARÉM | M40: PA | N40: CIDADE JARDIM IV | O40: Aquisição de Cotas | P40: 4800000 | Q40: Loteamento | R40: Sim | S40: 2028 | T40: 47118 | U40: 1 | W40: =SUM(U40:V40) -> 1 | AA40: 0.198 | AC40: =AI40*AJ40 -> 410455.51 | AE40: =P40/10^6 -> 4.8 | AF40: =IF(AL40=0,0,AE40/AL40) -> 0.023388649 | AG40: =(AH40*AI40*AJ40)/10^6 -> 54.631628 | AH40: 133.1 | AI40: 239.89217 | AJ40: 1711 | AK40: 500 | AL40: =(AK40*AJ40*AI40)/10^6 -> 205.22776 | AM40: =AL40*U40 -> 205.22776 | AN40: 119946.09 | AO40: =AH40*AI40 -> 31929.648 | AP40: =U40+AB40 -> 1 | AQ40: =AL40*AP40/(AG40+AE40) -> 3.453174
A41: MAP010 | B41: CIDADE JARDIM V - SANTARÉM | C41: https://earth.google.com/web/search/CIDADE+JARDIM+12+-+PARAUAPEBAS/@-2.45795692,-54.77217012,46.50042218a,6405.178905d,35y,-0h,0t,0r/data=CiwiJgokCdmVqMeMyQbAESVW3mJaMwnAGYI6tUF7jUfAIaCAQToN3EfAQgIIAToDCgEwQgIIAEoICJfn8a8FEAA | D41: 1 | E41: LandBank | G41: 2121 | J41: 150 | K41: NORTE | L41: SANTARÉM | M41: PA | N41: CIDADE JARDIM V | O41: Aquisição de Cotas | P41: 4800000 | Q41: Loteamento | R41: Sim | S41: 2030 | T41: 47848 | U41: 1 | W41: =SUM(U41:V41) -> 1 | AA41: 0.198 | AC41: =AI41*AJ41 -> 61214.16 | AE41: =P41/10^6 -> 4.8 | AF41: =IF(AL41=0,0,AE41/AL41) -> 0.15682646 | AG41: =(AH41*AI41*AJ41)/10^6 -> 8.1476047 | AH41: 133.1 | AI41: 275.73946 | AJ41: 222 | AK41: 500 | AL41: =(AK41*AJ41*AI41)/10^6 -> 30.60708 | AM41: =AL41*U41 -> 30.60708 | AN41: 137869.73 | AO41: =AH41*AI41 -> 36700.922 | AP41: =U41+AB41 -> 1 | AQ41: =AL41*AP41/(AG41+AE41) -> 2.3639183
A42: MAP011 | B42: CIDADE JARDIM VI - SANTARÉM | C42: https://earth.google.com/web/search/CIDADE+JARDIM+12+-+PARAUAPEBAS/@-2.45795692,-54.77217012,46.50042218a,6405.178905d,35y,-0h,0t,0r/data=CiwiJgokCdmVqMeMyQbAESVW3mJaMwnAGYI6tUF7jUfAIaCAQToN3EfAQgIIAToDCgEwQgIIAEoICJfn8a8FEAA | D42: 1 | E42: LandBank | G42: 2121 | J42: 151 | K42: NORTE | L42: SANTARÉM | M42: PA | N42: CIDADE JARDIM VI | O42: Aquisição de Cotas | P42: 4800000 | Q42: Loteamento | R42: Sim | S42: 2029 | T42: 47483 | U42: 1 | W42: =SUM(U42:V42) -> 1 | AA42: 0.198 | AC42: =AI42*AJ42 -> 319811.91 | AE42: =P42/10^6 -> 4.8 | AF42: =IF(AL42=0,0,AE42/AL42) -> 0.030017644 | AG42: =(AH42*AI42*AJ42)/10^6 -> 42.566965 | AH42: 133.1 | AI42: 366.33667 | AJ42: 873 | AK42: 500 | AL42: =(AK42*AJ42*AI42)/10^6 -> 159.90596 | AM42: =AL42*U42 -> 159.90596 | AN42: 183168.33 | AO42: =AH42*AI42 -> 48759.41 | AP42: =U42+AB42 -> 1 | AQ42: =AL42*AP42/(AG42+AE42) -> 3.3758961
A43: MAP012 | B43: RESIDENCIAL JARDIM IPIRANGA II - XINGUARA | C43: https://earth.google.com/web/search/RESIDENCIAL+JARDIM+IPIRANGA+II+-+XINGUARA/@-7.12104404,-49.92523395,224.47331647a,1424.00240818d,35y,-0h,0t,0r/data=CiwiJgokCUUfzO5U4h_AEV26WHYzKSDAGfKhedaB80jAITi3e0FBEEnAQgIIAToDCgEwQgIIAEoICJfn8a8FEAA?authuser=0 | D43: 1 | E43: LandBank | G43: 2118 | J43: 152 | K43: NORTE | L43: XINGUARA | M43: PA | N43: RESIDENCIAL JARDIM IPIRANGA II | O43: Parceria | P43: 0 | Q43: Loteamento | R43: Sim | S43: 2026 | T43: 46387 | U43: 1 | W43: =SUM(U43:V43) -> 1 | AA43: 0.198 | AC43: =AI43*AJ43 -> 195570.85 | AE43: =P43/10^6 -> 0 | AF43: =IF(AL43=0,0,AE43/AL43) -> 0 | AG43: =(AH43*AI43*AJ43)/10^6 -> 26.03048 | AH43: 133.1 | AI43: 210.97179 | AJ43: 927 | AK43: 430 | AL43: =(AK43*AJ43*AI43)/10^6 -> 84.095466 | AM43: =AL43*U43 -> 84.095466 | AN43: 90717.87 | AO43: =AH43*AI43 -> 28080.345 | AP43: =U43+AB43 -> 1 | AQ43: =AL43*AP43/(AG43+AE43) -> 3.2306536
A44: MAP013 | B44: RESIDENCIAL CIDADE JARDIM II - SANTANA DO ARAGUAIA | C44: https://earth.google.com/web/search/SANTANA+DO+ARAGUAIA/@-9.33586436,-50.36139721,175.24087708a,6146.88773774d,35y,0.00000002h,0t,0r/data=CoIBGlQSTgolMHg5MzFmMzU2MjJhMTljZmQxOjB4NDBiYzMzMTdkYTkxODA2NxkY0GYwoa0iwCGS2Q9nNCtJwCoTU0FOVEFOQSBETyBBUkFHVUFJQRgCIAEiJgokCSW03oMpdxzAEQai9168gBzAGSqKf2w09UjAIfPbVLWn90jAQgIIAToDCgEwQgIIAEoICJfn8a8FEAA?authuser=0 | D44: 1 | E44: LandBank | G44: 2123 | J44: 153 | K44: NORTE | L44: SANTANA DO ARAGUAIA | M44: PA | N44: RESIDENCIAL CIDADE JARDIM II | O44: Compra e Venda | P44: 114285.71 | Q44: Loteamento | R44: Sim | S44: 2028 | T44: 47118 | U44: 1 | W44: =SUM(U44:V44) -> 1 | AA44: 0.198 | AC44: =AI44*AJ44 -> 121800 | AE44: =P44/10^6 -> 0.11428571 | AF44: =IF(AL44=0,0,AE44/AL44) -> 0.0024059136 | AG44: =(AH44*AI44*AJ44)/10^6 -> 16.21158 | AH44: 133.1 | AI44: 210 | AJ44: 580 | AK44: 390 | AL44: =(AK44*AJ44*AI44)/10^6 -> 47.502 | AM44: =AL44*U44 -> 47.502 | AN44: 81900 | AO44: =AH44*AI44 -> 27951 | AP44: =U44+AB44 -> 1 | AQ44: =AL44*AP44/(AG44+AE44) -> 2.909616
A45: MAP013 | B45: RESIDENCIAL CIDADE JARDIM III - SANTANA DO ARAGUAIA | C45: https://earth.google.com/web/search/SANTANA+DO+ARAGUAIA/@-9.33586436,-50.36139721,175.24087708a,6146.88773774d,35y,0.00000002h,0t,0r/data=CoIBGlQSTgolMHg5MzFmMzU2MjJhMTljZmQxOjB4NDBiYzMzMTdkYTkxODA2NxkY0GYwoa0iwCGS2Q9nNCtJwCoTU0FOVEFOQSBETyBBUkFHVUFJQRgCIAEiJgokCSW03oMpdxzAEQai9168gBzAGSqKf2w09UjAIfPbVLWn90jAQgIIAToDCgEwQgIIAEoICJfn8a8FEAA?authuser=0 | D45: 1 | E45: LandBank | G45: 2123 | J45: 154 | K45: NORTE | L45: SANTANA DO ARAGUAIA | M45: PA | N45: RESIDENCIAL CIDADE JARDIM III | O45: Compra e Venda | P45: 114285.71 | Q45: Loteamento | R45: Sim | S45: 2030 | T45: 47848 | U45: 1 | W45: =SUM(U45:V45) -> 1 | AA45: 0.198 | AC45: =AI45*AJ45 -> 105000 | AE45: =P45/10^6 -> 0.11428571 | AF45: =IF(AL45=0,0,AE45/AL45) -> 0.0027908598 | AG45: =(AH45*AI45*AJ45)/10^6 -> 13.9755 | AH45: 133.1 | AI45: 210 | AJ45: 500 | AK45: 390 | AL45: =(AK45*AJ45*AI45)/10^6 -> 40.95 | AM45: =AL45*U45 -> 40.95 | AN45: 81900 | AO45: =AH45*AI45 -> 27951 | AP45: =U45+AB45 -> 1 | AQ45: =AL45*AP45/(AG45+AE45) -> 2.9063607
A46: MAP013 | B46: RESIDENCIAL CIDADE JARDIM IV - SANTANA DO ARAGUAIA | C46: https://earth.google.com/web/search/SANTANA+DO+ARAGUAIA/@-9.33586436,-50.36139721,175.24087708a,6146.88773774d,35y,0.00000002h,0t,0r/data=CoIBGlQSTgolMHg5MzFmMzU2MjJhMTljZmQxOjB4NDBiYzMzMTdkYTkxODA2NxkY0GYwoa0iwCGS2Q9nNCtJwCoTU0FOVEFOQSBETyBBUkFHVUFJQRgCIAEiJgokCSW03oMpdxzAEQai9168gBzAGSqKf2w09UjAIfPbVLWn90jAQgIIAToDCgEwQgIIAEoICJfn8a8FEAA?authuser=0 | D46: 1 | E46: LandBank | G46: 2123 | J46: 155 | K46: NORTE | L46: SANTANA DO ARAGUAIA | M46: PA | N46: RESIDENCIAL CIDADE JARDIM IV | O46: Compra e Venda | P46: 114285.71 | Q46: Loteamento | R46: Sim | S46: 2032 | T46: 48579 | U46: 1 | W46: =SUM(U46:V46) -> 1 | AA46: 0.198 | AC46: =AI46*AJ46 -> 105000 | AE46: =P46/10^6 -> 0.11428571 | AF46: =IF(AL46=0,0,AE46/AL46) -> 0.0027908598 | AG46: =(AH46*AI46*AJ46)/10^6 -> 13.9755 | AH46: 133.1 | AI46: 210 | AJ46: 500 | AK46: 390 | AL46: =(AK46*AJ46*AI46)/10^6 -> 40.95 | AM46: =AL46*U46 -> 40.95 | AN46: 81900 | AO46: =AH46*AI46 -> 27951 | AP46: =U46+AB46 -> 1 | AQ46: =AL46*AP46/(AG46+AE46) -> 2.9063607
A47: MAP013 | B47: RESIDENCIAL CIDADE JARDIM V - SANTANA DO ARAGUAIA | C47: https://earth.google.com/web/search/SANTANA+DO+ARAGUAIA/@-9.33586436,-50.36139721,175.24087708a,6146.88773774d,35y,0.00000002h,0t,0r/data=CoIBGlQSTgolMHg5MzFmMzU2MjJhMTljZmQxOjB4NDBiYzMzMTdkYTkxODA2NxkY0GYwoa0iwCGS2Q9nNCtJwCoTU0FOVEFOQSBETyBBUkFHVUFJQRgCIAEiJgokCSW03oMpdxzAEQai9168gBzAGSqKf2w09UjAIfPbVLWn90jAQgIIAToDCgEwQgIIAEoICJfn8a8FEAA?authuser=0 | D47: 1 | E47: LandBank | G47: 2123 | J47: 156 | K47: NORTE | L47: SANTANA DO ARAGUAIA | M47: PA | N47: RESIDENCIAL CIDADE JARDIM V | O47: Compra e Venda | P47: 114285.71 | Q47: Loteamento | R47: Sim | S47: 2034 | T47: 49309 | U47: 1 | W47: =SUM(U47:V47) -> 1 | AA47: 0.198 | AC47: =AI47*AJ47 -> 105000 | AE47: =P47/10^6 -> 0.11428571 | AF47: =IF(AL47=0,0,AE47/AL47) -> 0.0027908598 | AG47: =(AH47*AI47*AJ47)/10^6 -> 13.9755 | AH47: 133.1 | AI47: 210 | AJ47: 500 | AK47: 390 | AL47: =(AK47*AJ47*AI47)/10^6 -> 40.95 | AM47: =AL47*U47 -> 40.95 | AN47: 81900 | AO47: =AH47*AI47 -> 27951 | AP47: =U47+AB47 -> 1 | AQ47: =AL47*AP47/(AG47+AE47) -> 2.9063607
A48: MAP013 | B48: RESIDENCIAL CIDADE JARDIM VI - SANTANA DO ARAGUAIA | C48: https://earth.google.com/web/search/SANTANA+DO+ARAGUAIA/@-9.33586436,-50.36139721,175.24087708a,6146.88773774d,35y,0.00000002h,0t,0r/data=CoIBGlQSTgolMHg5MzFmMzU2MjJhMTljZmQxOjB4NDBiYzMzMTdkYTkxODA2NxkY0GYwoa0iwCGS2Q9nNCtJwCoTU0FOVEFOQSBETyBBUkFHVUFJQRgCIAEiJgokCSW03oMpdxzAEQai9168gBzAGSqKf2w09UjAIfPbVLWn90jAQgIIAToDCgEwQgIIAEoICJfn8a8FEAA?authuser=0 | D48: 1 | E48: LandBank | G48: 2123 | J48: 157 | K48: NORTE | L48: SANTANA DO ARAGUAIA | M48: PA | N48: RESIDENCIAL CIDADE JARDIM VI | O48: Compra e Venda | P48: 114285.71 | Q48: Loteamento | R48: Sim | S48: 2036 | T48: 50040 | U48: 1 | W48: =SUM(U48:V48) -> 1 | AA48: 0.198 | AC48: =AI48*AJ48 -> 105000 | AE48: =P48/10^6 -> 0.11428571 | AF48: =IF(AL48=0,0,AE48/AL48) -> 0.0027908598 | AG48: =(AH48*AI48*AJ48)/10^6 -> 13.9755 | AH48: 133.1 | AI48: 210 | AJ48: 500 | AK48: 390 | AL48: =(AK48*AJ48*AI48)/10^6 -> 40.95 | AM48: =AL48*U48 -> 40.95 | AN48: 81900 | AO48: =AH48*AI48 -> 27951 | AP48: =U48+AB48 -> 1 | AQ48: =AL48*AP48/(AG48+AE48) -> 2.9063607
A49: MAP013 | B49: RESIDENCIAL CIDADE JARDIM VII - SANTANA DO ARAGUAIA | C49: https://earth.google.com/web/search/SANTANA+DO+ARAGUAIA/@-9.33586436,-50.36139721,175.24087708a,6146.88773774d,35y,0.00000002h,0t,0r/data=CoIBGlQSTgolMHg5MzFmMzU2MjJhMTljZmQxOjB4NDBiYzMzMTdkYTkxODA2NxkY0GYwoa0iwCGS2Q9nNCtJwCoTU0FOVEFOQSBETyBBUkFHVUFJQRgCIAEiJgokCSW03oMpdxzAEQai9168gBzAGSqKf2w09UjAIfPbVLWn90jAQgIIAToDCgEwQgIIAEoICJfn8a8FEAA?authuser=0 | D49: 1 | E49: LandBank | G49: 2123 | J49: 158 | K49: NORTE | L49: SANTANA DO ARAGUAIA | M49: PA | N49: RESIDENCIAL CIDADE JARDIM VII | O49: Compra e Venda | P49: 114285.71 | Q49: Loteamento | R49: Sim | S49: 2038 | T49: 50770 | U49: 1 | W49: =SUM(U49:V49) -> 1 | AA49: 0.198 | AC49: =AI49*AJ49 -> 105000 | AE49: =P49/10^6 -> 0.11428571 | AF49: =IF(AL49=0,0,AE49/AL49) -> 0.0027908598 | AG49: =(AH49*AI49*AJ49)/10^6 -> 13.9755 | AH49: 133.1 | AI49: 210 | AJ49: 500 | AK49: 390 | AL49: =(AK49*AJ49*AI49)/10^6 -> 40.95 | AM49: =AL49*U49 -> 40.95 | AN49: 81900 | AO49: =AH49*AI49 -> 27951 | AP49: =U49+AB49 -> 1 | AQ49: =AL49*AP49/(AG49+AE49) -> 2.9063607
A50: MAP013 | B50: RESIDENCIAL CIDADE JARDIM VIII - SANTANA DO ARAGUAIA | C50: https://earth.google.com/web/search/SANTANA+DO+ARAGUAIA/@-9.33586436,-50.36139721,175.24087708a,6146.88773774d,35y,0.00000002h,0t,0r/data=CoIBGlQSTgolMHg5MzFmMzU2MjJhMTljZmQxOjB4NDBiYzMzMTdkYTkxODA2NxkY0GYwoa0iwCGS2Q9nNCtJwCoTU0FOVEFOQSBETyBBUkFHVUFJQRgCIAEiJgokCSW03oMpdxzAEQai9168gBzAGSqKf2w09UjAIfPbVLWn90jAQgIIAToDCgEwQgIIAEoICJfn8a8FEAA?authuser=0 | D50: 1 | E50: LandBank | G50: 2123 | J50: 159 | K50: NORTE | L50: SANTANA DO ARAGUAIA | M50: PA | N50: RESIDENCIAL CIDADE JARDIM VIII | O50: Compra e Venda | P50: 114285.71 | Q50: Loteamento | R50: Sim | S50: 2040 | T50: 51501 | U50: 1 | W50: =SUM(U50:V50) -> 1 | AA50: 0.198 | AC50: =AI50*AJ50 -> 105000 | AE50: =P50/10^6 -> 0.11428571 | AF50: =IF(AL50=0,0,AE50/AL50) -> 0.0027908598 | AG50: =(AH50*AI50*AJ50)/10^6 -> 13.9755 | AH50: 133.1 | AI50: 210 | AJ50: 500 | AK50: 390 | AL50: =(AK50*AJ50*AI50)/10^6 -> 40.95 | AM50: =AL50*U50 -> 40.95 | AN50: 81900 | AO50: =AH50*AI50 -> 27951 | AP50: =U50+AB50 -> 1 | AQ50: =AL50*AP50/(AG50+AE50) -> 2.9063607
A51: MAP020 | B51: A DEFINIR - OURILÂNDIA DO NORTE | C51: https://earth.google.com/web/search/OURIL%c3%82NDIA+DO+NORTE/@-6.76332079,-51.09501931,271.46517916a,4119.95438506d,35y,0h,0t,0r/data=CoMBGlUSTwolMHg5MmU2OGRmYTEzMDRmZDU1OjB4ODI4Zjg0ZGJmZDc3Y2IyNhlvfsNEgwQbwCFX3p-csohJwCoUT1VSSUzDgk5ESUEgRE8gTk9SVEUYASABIiYKJAnmKm6ixaIiwBENEmgyIrUiwBm022ofiSlJwCGWj1zi_DJJwEICCAE6AwoBMEICCABKCAiX5_GvBRAA?authuser=0 | D51: 1 | E51: LandBank | G51: 2120 | J51: 160 | K51: NORTE | L51: OURILÂNDIA DO NORTE | M51: PA | N51: A DEFINIR | O51: Compra e Venda | P51: 9700000 | Q51: Loteamento | R51: - | S51: - | T51: - | U51: 1 | W51: =SUM(U51:V51) -> 1 | AA51: 0.198 | AC51: =AI51*AJ51 -> 751970 | AE51: =P51/10^6 -> 9.7 | AF51: =IF(AL51=0,0,AE51/AL51) -> 0.194 | AG51: =(AH51*AI51*AJ51)/10^6 -> 60.1576 | AH51: 80 | AI51: 1503.94 | AJ51: 500 | AK51: 66.492014 | AL51: =(AK51*AJ51*AI51)/10^6 -> 50 | AM51: =AL51*U51 -> 50 | AN51: 100000 | AO51: =AH51*AI51 -> 120315.2 | AP51: =U51+AB51 -> 1 | AQ51: =AL51*AP51/(AG51+AE51) -> 0.71574174
A52: MAP004 | B52: CIDADE JARDIM 12 - PARAUAPEBAS | C52: https://earth.google.com/web/search/CIDADE+JARDIM+12+-+PARAUAPEBAS/@-6.04487592,-49.83564552,181.81336445a,9406.37838209d,35y,0h,0t,0r/data=CiwiJgokCS03B0TTPhXAEXKT3p9G5BrAGSZGC1wr6UfAISLEcDjXWknAQgIIAToDCgEwQgIIAEoICJfn8a8FEAA?authuser=0 | D52: 1 | E52: LandBank | G52: 2584 | J52: 139 | K52: NORTE | L52: PARAUAPEBAS | M52: PA | N52: CIDADE JARDIM 12 | O52: Compra e Venda | P52: 4000000 | Q52: Loteamento | R52: Sim | S52: 2026 | T52: 46387 | U52: 1 | W52: =SUM(U52:V52) -> 1 | AA52: 0.198 | AC52: =AI52*AJ52 -> 297407.69 | AE52: =P52/10^6 -> 4 | AF52: =IF(AL52=0,0,AE52/AL52) -> 0.022415919 | AG52: =(AH52*AI52*AJ52)/10^6 -> 39.584964 | AH52: 133.1 | AI52: 216.61157 | AJ52: 1373 | AK52: 600 | AL52: =(AK52*AJ52*AI52)/10^6 -> 178.44461 | AM52: =AL52*U52 -> 178.44461 | AN52: 129966.94 | AO52: =AH52*AI52 -> 28831 | AP52: =U52+AB52 -> 1 | AQ52: =AL52*AP52/(AG52+AE52) -> 4.0941783
A53: MAP005 | B53: CIDADE JARDIM 13 - PARAUAPEBAS | C53: https://earth.google.com/web/search/CIDADE+JARDIM+12+-+PARAUAPEBAS/@-6.04487592,-49.83564552,181.81336445a,9406.37838209d,35y,0h,0t,0r/data=CiwiJgokCS03B0TTPhXAEXKT3p9G5BrAGSZGC1wr6UfAISLEcDjXWknAQgIIAToDCgEwQgIIAEoICJfn8a8FEAA?authuser=0 | D53: 0 | E53: LandBank | G53: Inativo | J53: 140 | K53: NORTE | L53: PARAUAPEBAS | M53: PA | N53: CIDADE JARDIM 13 | O53: Parceria | P53: 0 | Q53: Loteamento | R53: - | S53: 2028 | T53: 47118 | U53: 0.9 | W53: =SUM(U53:V53) -> 0.9 | AA53: 0.198 | AB53: 0.1 | AC53: =AI53*AJ53 -> 197371.09 | AE53: =P53/10^6 -> 0 | AF53: =IF(AL53=0,0,AE53/AL53) -> 0 | AG53: =(AH53*AI53*AJ53)/10^6 -> 26.270092 | AH53: 133.1 | AI53: 219.30121 | AJ53: 900 | AK53: 600 | AL53: =(AK53*AJ53*AI53)/10^6 -> 118.42266 | AM53: =AL53*U53 -> 106.58039 | AN53: 131580.73 | AO53: =AH53*AI53 -> 29188.992 | AP53: =U53+AB53 -> 1 | AQ53: =AL53*AP53/(AG53+AE53) -> 4.5078888
A54: MAP005 | B54: CIDADE JARDIM 14 - PARAUAPEBAS | C54: https://earth.google.com/web/search/CIDADE+JARDIM+12+-+PARAUAPEBAS/@-6.04487592,-49.83564552,181.81336445a,9406.37838209d,35y,0h,0t,0r/data=CiwiJgokCS03B0TTPhXAEXKT3p9G5BrAGSZGC1wr6UfAISLEcDjXWknAQgIIAToDCgEwQgIIAEoICJfn8a8FEAA?authuser=0 | D54: 0 | E54: LandBank | G54: Inativo | J54: 141 | K54: NORTE | L54: PARAUAPEBAS | M54: PA | N54: CIDADE JARDIM 14 | O54: Parceria | P54: 0 | Q54: Loteamento | R54: - | S54: 2029 | T54: 47483 | U54: 0.9 | W54: =SUM(U54:V54) -> 0.9 | AA54: 0.198 | AB54: 0.1 | AC54: =AI54*AJ54 -> 174125.16 | AE54: =P54/10^6 -> 0 | AF54: =IF(AL54=0,0,AE54/AL54) -> 0 | AG54: =(AH54*AI54*AJ54)/10^6 -> 23.176059 | AH54: 133.1 | AI54: 219.30121 | AJ54: 794 | AK54: 600 | AL54: =(AK54*AJ54*AI54)/10^6 -> 104.4751 | AM54: =AL54*U54 -> 94.027589 | AN54: 131580.73 | AO54: =AH54*AI54 -> 29188.992 | AP54: =U54+AB54 -> 1 | AQ54: =AL54*AP54/(AG54+AE54) -> 4.5078888
A55: MAP005 | B55: CIDADE JARDIM 15 - PARAUAPEBAS | C55: https://earth.google.com/web/search/CIDADE+JARDIM+12+-+PARAUAPEBAS/@-6.04487592,-49.83564552,181.81336445a,9406.37838209d,35y,0h,0t,0r/data=CiwiJgokCS03B0TTPhXAEXKT3p9G5BrAGSZGC1wr6UfAISLEcDjXWknAQgIIAToDCgEwQgIIAEoICJfn8a8FEAA?authuser=0 | D55: 0 | E55: LandBank | G55: Inativo | J55: 142 | K55: NORTE | L55: PARAUAPEBAS | M55: PA | N55: CIDADE JARDIM 15 | O55: Parceria | P55: 0 | Q55: Loteamento | R55: - | S55: 2030 | T55: 47848 | U55: 0.9 | W55: =SUM(U55:V55) -> 0.9 | AA55: 0.198 | AB55: 0.1 | AC55: =AI55*AJ55 -> 183116.51 | AE55: =P55/10^6 -> 0 | AF55: =IF(AL55=0,0,AE55/AL55) -> 0 | AG55: =(AH55*AI55*AJ55)/10^6 -> 24.372808 | AH55: 133.1 | AI55: 219.30121 | AJ55: 835 | AK55: 600 | AL55: =(AK55*AJ55*AI55)/10^6 -> 109.86991 | AM55: =AL55*U55 -> 98.882918 | AN55: 131580.73 | AO55: =AH55*AI55 -> 29188.992 | AP55: =U55+AB55 -> 1 | AQ55: =AL55*AP55/(AG55+AE55) -> 4.5078888
A56: MAP005 | B56: CIDADE JARDIM 16 - PARAUAPEBAS | C56: https://earth.google.com/web/search/CIDADE+JARDIM+12+-+PARAUAPEBAS/@-6.04487592,-49.83564552,181.81336445a,9406.37838209d,35y,0h,0t,0r/data=CiwiJgokCS03B0TTPhXAEXKT3p9G5BrAGSZGC1wr6UfAISLEcDjXWknAQgIIAToDCgEwQgIIAEoICJfn8a8FEAA?authuser=0 | D56: 0 | E56: LandBank | G56: Inativo | J56: 143 | K56: NORTE | L56: PARAUAPEBAS | M56: PA | N56: CIDADE JARDIM 16 | O56: Parceria | P56: 0 | Q56: Loteamento | R56: - | S56: 2031 | T56: 48213 | U56: 0.9 | W56: =SUM(U56:V56) -> 0.9 | AA56: 0.198 | AB56: 0.1 | AC56: =AI56*AJ56 -> 183116.51 | AE56: =P56/10^6 -> 0 | AF56: =IF(AL56=0,0,AE56/AL56) -> 0 | AG56: =(AH56*AI56*AJ56)/10^6 -> 24.372808 | AH56: 133.1 | AI56: 219.30121 | AJ56: 835 | AK56: 600 | AL56: =(AK56*AJ56*AI56)/10^6 -> 109.86991 | AM56: =AL56*U56 -> 98.882918 | AN56: 131580.73 | AO56: =AH56*AI56 -> 29188.992 | AP56: =U56+AB56 -> 1 | AQ56: =AL56*AP56/(AG56+AE56) -> 4.5078888
A57: MAP005 | B57: CIDADE JARDIM 17 - PARAUAPEBAS | C57: https://earth.google.com/web/search/CIDADE+JARDIM+12+-+PARAUAPEBAS/@-6.04487592,-49.83564552,181.81336445a,9406.37838209d,35y,0h,0t,0r/data=CiwiJgokCS03B0TTPhXAEXKT3p9G5BrAGSZGC1wr6UfAISLEcDjXWknAQgIIAToDCgEwQgIIAEoICJfn8a8FEAA?authuser=0 | D57: 0 | E57: LandBank | G57: Inativo | J57: 144 | K57: NORTE | L57: PARAUAPEBAS | M57: PA | N57: CIDADE JARDIM 17 | O57: Parceria | P57: 0 | Q57: Loteamento | R57: - | S57: 2032 | T57: 48579 | U57: 0.9 | W57: =SUM(U57:V57) -> 0.9 | AA57: 0.198 | AB57: 0.1 | AC57: =AI57*AJ57 -> 183116.51 | AE57: =P57/10^6 -> 0 | AF57: =IF(AL57=0,0,AE57/AL57) -> 0 | AG57: =(AH57*AI57*AJ57)/10^6 -> 24.372808 | AH57: 133.1 | AI57: 219.30121 | AJ57: 835 | AK57: 600 | AL57: =(AK57*AJ57*AI57)/10^6 -> 109.86991 | AM57: =AL57*U57 -> 98.882918 | AN57: 131580.73 | AO57: =AH57*AI57 -> 29188.992 | AP57: =U57+AB57 -> 1 | AQ57: =AL57*AP57/(AG57+AE57) -> 4.5078888
A58: MAP121 | B58: RES. BURITI GARDEN - CONCEIÇÃO DO ARAGUAIA | C58: https://earth.google.com/web/search/CONCEI%c3%87%c3%83O+DO+ARAGUAIA/@-8.36662137,-49.28837855,171.07324722a,4098.20934676d,35y,-0h,0t,0r/data=CoYBGlgSUgolMHg5MzIwOGVkOGNlMjM0NzkxOjB4YTkyMzUwNTBlYzEzOTgxYhn3G5L_boYgwCGiLq3hfaJIwCoXQ09OQ0VJw4fDg08gRE8gQVJBR1VBSUEYASABIiYKJAmUyRpDBqgwwBHbTnQb0LIwwBktQ1q_GrJIwCGoHPQLYbtIwEICCAE6AwoBMEICCABKCAiX5_GvBRAA?authuser=0 | D58: 1 | E58: LandBank | G58: 2773 | J58: 357 | K58: NORTE | L58: CONCEIÇÃO DO ARAGUAIA | M58: PA | N58: RES. BURITI GARDEN | O58: Parceria | P58: 0 | Q58: Condominio | R58: - | S58: 2026 | T58: 46203 | U58: 1 | W58: =SUM(U58:V58) -> 1 | AA58: 0.198 | AC58: =AI58*AJ58 -> 75000 | AE58: =P58/10^6 -> 0 | AF58: =IF(AL58=0,0,AE58/AL58) -> 0 | AG58: =(AH58*AI58*AJ58)/10^6 -> 19.5 | AH58: 260 | AI58: 300 | AJ58: 250 | AK58: 700 | AL58: =(AK58*AJ58*AI58)/10^6 -> 52.5 | AM58: =AL58*U58 -> 52.5 | AN58: 210000 | AO58: =AH58*AI58 -> 78000 | AP58: =U58+AB58 -> 1 | AQ58: =AL58*AP58/(AG58+AE58) -> 2.6923077
A59: MAP113 | B59: BURITI GARDEN PRIME - VARZEA GRANDE | C59: https://earth.google.com/web/search/CUIAB%c3%81/@-15.61005921,-56.15084275,175.93804739a,4592.0123658d,35y,0h,0t,0r/data=CiwiJgokCTDbVLh45ybAEXD1A07O7ybAGaZZUBA5uU7AIdT4-d2KvU7AQgIIAToDCgEwQgIIAEoICJfn8a8FEAA?authuser=0 | D59: 1 | E59: LandBank | G59: 1930 | J59: 346 | K59: OESTE | L59: VARZEA GRANDE | M59: MT | N59: BURITI GARDEN PRIME | O59: Parceria | P59: 0 | Q59: Condominio | R59: - | S59: 2030 | T59: 47664 | U59: 0.7 | V59: 0.3 | W59: =SUM(U59:V59) -> 1 | X59: 0.05 | Y59: 0.09 | Z59: 0.068 | AA59: 0.198 | AC59: =AI59*AJ59 -> 139700 | AE59: =P59/10^6 -> 0 | AF59: =IF(AL59=0,0,AE59/AL59) -> 0 | AG59: =(AH59*AI59*AJ59)/10^6 -> 36.322 | AH59: 260 | AI59: 220 | AJ59: 635 | AK59: 1200 | AL59: =(AK59*AJ59*AI59)/10^6 -> 167.64 | AM59: =AL59*U59 -> 117.348 | AN59: 264000 | AO59: =AH59*AI59 -> 57200 | AP59: =U59+AB59 -> 0.7 | AQ59: =AL59*AP59/(AG59+AE59) -> 3.2307692
A60: MAP106 | B60: RESIDENCIAL CIDADE JARDIM II - RIO BRANCO | C60: https://earth.google.com/web/search/RIO+BRANCO/@-9.9098996,-67.78102104,162.15508008a,8113.58158257d,35y,360h,0t,0r/data=CnkaSxJFCiUweDkxN2Y3YmI2OGFjYzk2ZjM6MHg4YWI4OGYxZDdmMWQ5YjNjGbb6RWSz8iPAIUaLfRPU81DAKgpSSU8gQlJBTkNPGAEgASImCiQJfzD99xEWMMAR4w_EqB0hMMAZ8L7dRwvPTMAhtzjkj7naTMBCAggBOgMKATBCAggASggIl-fxrwUQAA?authuser=0 | D60: 1 | E60: LandBank | G60: 2106 | J60: 326 | K60: OESTE | L60: RIO BRANCO | M60: AC | N60: RESIDENCIAL CIDADE JARDIM II | O60: Compra e Venda | P60: 1436252.3 | Q60: Loteamento | R60: Sim | S60: 2029 | T60: 47483 | U60: 0.7 | V60: 0.3 | W60: =SUM(U60:V60) -> 1 | X60: 0.05 | Y60: 0.09 | Z60: 0.068 | AA60: 0.198 | AC60: =AI60*AJ60 -> 248211 | AE60: =P60/10^6 -> 1.4362523 | AF60: =IF(AL60=0,0,AE60/AL60) -> 0.011572834 | AG60: =(AH60*AI60*AJ60)/10^6 -> 39.71376 | AH60: 160 | AI60: 261 | AJ60: 951 | AK60: 500 | AL60: =(AK60*AJ60*AI60)/10^6 -> 124.1055 | AM60: =AL60*U60 -> 86.87385 | AN60: 110000 | AO60: =AH60*AI60 -> 41760 | AP60: =U60+AB60 -> 0.7 | AQ60: =AL60*AP60/(AG60+AE60) -> 2.11115
A61: MAP106 | B61: RESIDENCIAL CIDADE JARDIM II - STP 2 - RIO BRANCO | C61: https://earth.google.com/web/search/RIO+BRANCO/@-9.9098996,-67.78102104,162.15508008a,8113.58158257d,35y,360h,0t,0r/data=CnkaSxJFCiUweDkxN2Y3YmI2OGFjYzk2ZjM6MHg4YWI4OGYxZDdmMWQ5YjNjGbb6RWSz8iPAIUaLfRPU81DAKgpSSU8gQlJBTkNPGAEgASImCiQJfzD99xEWMMAR4w_EqB0hMMAZ8L7dRwvPTMAhtzjkj7naTMBCAggBOgMKATBCAggASggIl-fxrwUQAA?authuser=0 | D61: 1 | E61: LandBank | G61: 2106 | J61: 327 | K61: OESTE | L61: RIO BRANCO | M61: AC | N61: RESIDENCIAL CIDADE JARDIM II - STP 2 | O61: Compra e Venda | P61: 1436252.3 | Q61: Loteamento | R61: Sim | S61: 2031 | T61: 48029 | U61: 0.7 | V61: 0.3 | W61: =SUM(U61:V61) -> 1 | X61: 0.05 | Y61: 0.09 | Z61: 0.068 | AA61: 0.198 | AC61: =AI61*AJ61 -> 248211 | AE61: =P61/10^6 -> 1.4362523 | AF61: =IF(AL61=0,0,AE61/AL61) -> 0.011572834 | AG61: =(AH61*AI61*AJ61)/10^6 -> 39.71376 | AH61: 160 | AI61: 261 | AJ61: 951 | AK61: 500 | AL61: =(AK61*AJ61*AI61)/10^6 -> 124.1055 | AM61: =AL61*U61 -> 86.87385 | AN61: 110000 | AO61: =AH61*AI61 -> 41760 | AP61: =U61+AB61 -> 0.7 | AQ61: =AL61*AP61/(AG61+AE61) -> 2.11115
A62: MAP107 | B62: RESIDENCIAL CIDADE JARDIM IV - RIO BRANCO | C62: https://earth.google.com/web/search/RIO+BRANCO/@-9.9098996,-67.78102104,162.15508008a,8113.58158257d,35y,360h,0t,0r/data=CnkaSxJFCiUweDkxN2Y3YmI2OGFjYzk2ZjM6MHg4YWI4OGYxZDdmMWQ5YjNjGbb6RWSz8iPAIUaLfRPU81DAKgpSSU8gQlJBTkNPGAEgASImCiQJfzD99xEWMMAR4w_EqB0hMMAZ8L7dRwvPTMAhtzjkj7naTMBCAggBOgMKATBCAggASggIl-fxrwUQAA?authuser=0 | D62: 1 | E62: LandBank | G62: 2106 | J62: 328 | K62: OESTE | L62: RIO BRANCO | M62: AC | N62: RESIDENCIAL CIDADE JARDIM IV | O62: Compra e Venda | P62: 1436252.3 | Q62: Loteamento | R62: - | S62: 2033 | T62: 48760 | U62: 0.7 | V62: 0.3 | W62: =SUM(U62:V62) -> 1 | X62: 0.05 | Y62: 0.09 | Z62: 0.068 | AA62: 0.198 | AC62: =AI62*AJ62 -> 232066.43 | AE62: =P62/10^6 -> 1.4362523 | AF62: =IF(AL62=0,0,AE62/AL62) -> 0.012377941 | AG62: =(AH62*AI62*AJ62)/10^6 -> 37.130628 | AH62: 160 | AI62: 270.15882 | AJ62: 859 | AK62: 500 | AL62: =(AK62*AJ62*AI62)/10^6 -> 116.03321 | AM62: =AL62*U62 -> 81.223249 | AN62: 135079.41 | AO62: =AH62*AI62 -> 43225.411 | AP62: =U62+AB62 -> 0.7 | AQ62: =AL62*AP62/(AG62+AE62) -> 2.1060363
A63: MAP107 | B63: RESIDENCIAL CIDADE JARDIM V - RIO BRANCO | C63: https://earth.google.com/web/search/RIO+BRANCO/@-9.9098996,-67.78102104,162.15508008a,8113.58158257d,35y,360h,0t,0r/data=CnkaSxJFCiUweDkxN2Y3YmI2OGFjYzk2ZjM6MHg4YWI4OGYxZDdmMWQ5YjNjGbb6RWSz8iPAIUaLfRPU81DAKgpSSU8gQlJBTkNPGAEgASImCiQJfzD99xEWMMAR4w_EqB0hMMAZ8L7dRwvPTMAhtzjkj7naTMBCAggBOgMKATBCAggASggIl-fxrwUQAA?authuser=0 | D63: 1 | E63: LandBank | G63: 2106 | J63: 329 | K63: OESTE | L63: RIO BRANCO | M63: AC | N63: RESIDENCIAL CIDADE JARDIM V | O63: Compra e Venda | P63: 1436252.3 | Q63: Loteamento | R63: - | S63: 2035 | T63: 49490 | U63: 0.7 | V63: 0.3 | W63: =SUM(U63:V63) -> 1 | X63: 0.05 | Y63: 0.09 | Z63: 0.068 | AA63: 0.198 | AC63: =AI63*AJ63 -> 232066.43 | AE63: =P63/10^6 -> 1.4362523 | AF63: =IF(AL63=0,0,AE63/AL63) -> 0.012377941 | AG63: =(AH63*AI63*AJ63)/10^6 -> 37.130628 | AH63: 160 | AI63: 270.15882 | AJ63: 859 | AK63: 500 | AL63: =(AK63*AJ63*AI63)/10^6 -> 116.03321 | AM63: =AL63*U63 -> 81.223249 | AN63: 135079.41 | AO63: =AH63*AI63 -> 43225.411 | AP63: =U63+AB63 -> 0.7 | AQ63: =AL63*AP63/(AG63+AE63) -> 2.1060363
A64: MAP107 | B64: RESIDENCIAL CIDADE JARDIM VI - RIO BRANCO | C64: https://earth.google.com/web/search/RIO+BRANCO/@-9.9098996,-67.78102104,162.15508008a,8113.58158257d,35y,360h,0t,0r/data=CnkaSxJFCiUweDkxN2Y3YmI2OGFjYzk2ZjM6MHg4YWI4OGYxZDdmMWQ5YjNjGbb6RWSz8iPAIUaLfRPU81DAKgpSSU8gQlJBTkNPGAEgASImCiQJfzD99xEWMMAR4w_EqB0hMMAZ8L7dRwvPTMAhtzjkj7naTMBCAggBOgMKATBCAggASggIl-fxrwUQAA?authuser=0 | D64: 1 | E64: LandBank | G64: 2106 | J64: 330 | K64: OESTE | L64: RIO BRANCO | M64: AC | N64: RESIDENCIAL CIDADE JARDIM VI | O64: Compra e Venda | P64: 1436252.3 | Q64: Loteamento | R64: - | S64: 2037 | T64: 50221 | U64: 0.7 | V64: 0.3 | W64: =SUM(U64:V64) -> 1 | X64: 0.05 | Y64: 0.09 | Z64: 0.068 | AA64: 0.198 | AC64: =AI64*AJ64 -> 232066.43 | AE64: =P64/10^6 -> 1.4362523 | AF64: =IF(AL64=0,0,AE64/AL64) -> 0.012377941 | AG64: =(AH64*AI64*AJ64)/10^6 -> 37.130628 | AH64: 160 | AI64: 270.15882 | AJ64: 859 | AK64: 500 | AL64: =(AK64*AJ64*AI64)/10^6 -> 116.03321 | AM64: =AL64*U64 -> 81.223249 | AN64: 135079.41 | AO64: =AH64*AI64 -> 43225.411 | AP64: =U64+AB64 -> 0.7 | AQ64: =AL64*AP64/(AG64+AE64) -> 2.1060363
A65: MAP107 | B65: RESIDENCIAL CIDADE JARDIM VII - RIO BRANCO | C65: https://earth.google.com/web/search/RIO+BRANCO/@-9.9098996,-67.78102104,162.15508008a,8113.58158257d,35y,360h,0t,0r/data=CnkaSxJFCiUweDkxN2Y3YmI2OGFjYzk2ZjM6MHg4YWI4OGYxZDdmMWQ5YjNjGbb6RWSz8iPAIUaLfRPU81DAKgpSSU8gQlJBTkNPGAEgASImCiQJfzD99xEWMMAR4w_EqB0hMMAZ8L7dRwvPTMAhtzjkj7naTMBCAggBOgMKATBCAggASggIl-fxrwUQAA?authuser=0 | D65: 1 | E65: LandBank | G65: 2106 | J65: 331 | K65: OESTE | L65: RIO BRANCO | M65: AC | N65: RESIDENCIAL CIDADE JARDIM VII | O65: Compra e Venda | P65: 1436252.3 | Q65: Loteamento | R65: - | S65: 2039 | T65: 50951 | U65: 0.7 | V65: 0.3 | W65: =SUM(U65:V65) -> 1 | X65: 0.05 | Y65: 0.09 | Z65: 0.068 | AA65: 0.198 | AC65: =AI65*AJ65 -> 232066.43 | AE65: =P65/10^6 -> 1.4362523 | AF65: =IF(AL65=0,0,AE65/AL65) -> 0.012377941 | AG65: =(AH65*AI65*AJ65)/10^6 -> 37.130628 | AH65: 160 | AI65: 270.15882 | AJ65: 859 | AK65: 500 | AL65: =(AK65*AJ65*AI65)/10^6 -> 116.03321 | AM65: =AL65*U65 -> 81.223249 | AN65: 135079.41 | AO65: =AH65*AI65 -> 43225.411 | AP65: =U65+AB65 -> 0.7 | AQ65: =AL65*AP65/(AG65+AE65) -> 2.1060363
A66: MAP107 | B66: RESIDENCIAL CIDADE JARDIM VIII - RIO BRANCO | C66: https://earth.google.com/web/search/RIO+BRANCO/@-9.9098996,-67.78102104,162.15508008a,8113.58158257d,35y,360h,0t,0r/data=CnkaSxJFCiUweDkxN2Y3YmI2OGFjYzk2ZjM6MHg4YWI4OGYxZDdmMWQ5YjNjGbb6RWSz8iPAIUaLfRPU81DAKgpSSU8gQlJBTkNPGAEgASImCiQJfzD99xEWMMAR4w_EqB0hMMAZ8L7dRwvPTMAhtzjkj7naTMBCAggBOgMKATBCAggASggIl-fxrwUQAA?authuser=0 | D66: 1 | E66: LandBank | G66: 2106 | J66: 332 | K66: OESTE | L66: RIO BRANCO | M66: AC | N66: RESIDENCIAL CIDADE JARDIM VIII | O66: Compra e Venda | P66: 1436252.3 | Q66: Loteamento | R66: - | S66: 2041 | T66: 51682 | U66: 0.7 | V66: 0.3 | W66: =SUM(U66:V66) -> 1 | X66: 0.05 | Y66: 0.09 | Z66: 0.068 | AA66: 0.198 | AC66: =AI66*AJ66 -> 232066.43 | AE66: =P66/10^6 -> 1.4362523 | AF66: =IF(AL66=0,0,AE66/AL66) -> 0.012377941 | AG66: =(AH66*AI66*AJ66)/10^6 -> 37.130628 | AH66: 160 | AI66: 270.15882 | AJ66: 859 | AK66: 500 | AL66: =(AK66*AJ66*AI66)/10^6 -> 116.03321 | AM66: =AL66*U66 -> 81.223249 | AN66: 135079.41 | AO66: =AH66*AI66 -> 43225.411 | AP66: =U66+AB66 -> 0.7 | AQ66: =AL66*AP66/(AG66+AE66) -> 2.1060363
A67: MAP107 | B67: RESIDENCIAL CIDADE JARDIM IX - RIO BRANCO | C67: https://earth.google.com/web/search/RIO+BRANCO/@-9.9098996,-67.78102104,162.15508008a,8113.58158257d,35y,360h,0t,0r/data=CnkaSxJFCiUweDkxN2Y3YmI2OGFjYzk2ZjM6MHg4YWI4OGYxZDdmMWQ5YjNjGbb6RWSz8iPAIUaLfRPU81DAKgpSSU8gQlJBTkNPGAEgASImCiQJfzD99xEWMMAR4w_EqB0hMMAZ8L7dRwvPTMAhtzjkj7naTMBCAggBOgMKATBCAggASggIl-fxrwUQAA?authuser=0 | D67: 1 | E67: LandBank | G67: 2106 | J67: 333 | K67: OESTE | L67: RIO BRANCO | M67: AC | N67: RESIDENCIAL CIDADE JARDIM IX | O67: Compra e Venda | P67: 1436252.3 | Q67: Loteamento | R67: - | S67: 2043 | T67: 52412 | U67: 0.7 | V67: 0.3 | W67: =SUM(U67:V67) -> 1 | X67: 0.05 | Y67: 0.09 | Z67: 0.068 | AA67: 0.198 | AC67: =AI67*AJ67 -> 232066.43 | AE67: =P67/10^6 -> 1.4362523 | AF67: =IF(AL67=0,0,AE67/AL67) -> 0.012377941 | AG67: =(AH67*AI67*AJ67)/10^6 -> 37.130628 | AH67: 160 | AI67: 270.15882 | AJ67: 859 | AK67: 500 | AL67: =(AK67*AJ67*AI67)/10^6 -> 116.03321 | AM67: =AL67*U67 -> 81.223249 | AN67: 135079.41 | AO67: =AH67*AI67 -> 43225.411 | AP67: =U67+AB67 -> 0.7 | AQ67: =AL67*AP67/(AG67+AE67) -> 2.1060363
A68: MAP107 | B68: RESIDENCIAL CIDADE JARDIM X - RIO BRANCO | C68: https://earth.google.com/web/search/RIO+BRANCO/@-9.9098996,-67.78102104,162.15508008a,8113.58158257d,35y,360h,0t,0r/data=CnkaSxJFCiUweDkxN2Y3YmI2OGFjYzk2ZjM6MHg4YWI4OGYxZDdmMWQ5YjNjGbb6RWSz8iPAIUaLfRPU81DAKgpSSU8gQlJBTkNPGAEgASImCiQJfzD99xEWMMAR4w_EqB0hMMAZ8L7dRwvPTMAhtzjkj7naTMBCAggBOgMKATBCAggASggIl-fxrwUQAA?authuser=0 | D68: 1 | E68: LandBank | G68: 2106 | J68: 334 | K68: OESTE | L68: RIO BRANCO | M68: AC | N68: RESIDENCIAL CIDADE JARDIM X | O68: Compra e Venda | P68: 1436252.3 | Q68: Loteamento | R68: - | S68: 2045 | T68: 53143 | U68: 0.7 | V68: 0.3 | W68: =SUM(U68:V68) -> 1 | X68: 0.05 | Y68: 0.09 | Z68: 0.068 | AA68: 0.198 | AC68: =AI68*AJ68 -> 232066.43 | AE68: =P68/10^6 -> 1.4362523 | AF68: =IF(AL68=0,0,AE68/AL68) -> 0.012377941 | AG68: =(AH68*AI68*AJ68)/10^6 -> 37.130628 | AH68: 160 | AI68: 270.15882 | AJ68: 859 | AK68: 500 | AL68: =(AK68*AJ68*AI68)/10^6 -> 116.03321 | AM68: =AL68*U68 -> 81.223249 | AN68: 135079.41 | AO68: =AH68*AI68 -> 43225.411 | AP68: =U68+AB68 -> 0.7 | AQ68: =AL68*AP68/(AG68+AE68) -> 2.1060363
A69: MAP107 | B69: RESIDENCIAL CIDADE JARDIM XI - RIO BRANCO | C69: https://earth.google.com/web/search/RIO+BRANCO/@-9.9098996,-67.78102104,162.15508008a,8113.58158257d,35y,360h,0t,0r/data=CnkaSxJFCiUweDkxN2Y3YmI2OGFjYzk2ZjM6MHg4YWI4OGYxZDdmMWQ5YjNjGbb6RWSz8iPAIUaLfRPU81DAKgpSSU8gQlJBTkNPGAEgASImCiQJfzD99xEWMMAR4w_EqB0hMMAZ8L7dRwvPTMAhtzjkj7naTMBCAggBOgMKATBCAggASggIl-fxrwUQAA?authuser=0 | D69: 1 | E69: LandBank | G69: 2106 | J69: 335 | K69: OESTE | L69: RIO BRANCO | M69: AC | N69: RESIDENCIAL CIDADE JARDIM XI | O69: Compra e Venda | P69: 1436252.3 | Q69: Loteamento | R69: - | S69: 2047 | T69: 53873 | U69: 0.7 | V69: 0.3 | W69: =SUM(U69:V69) -> 1 | X69: 0.05 | Y69: 0.09 | Z69: 0.068 | AA69: 0.198 | AC69: =AI69*AJ69 -> 232066.43 | AE69: =P69/10^6 -> 1.4362523 | AF69: =IF(AL69=0,0,AE69/AL69) -> 0.012377941 | AG69: =(AH69*AI69*AJ69)/10^6 -> 37.130628 | AH69: 160 | AI69: 270.15882 | AJ69: 859 | AK69: 500 | AL69: =(AK69*AJ69*AI69)/10^6 -> 116.03321 | AM69: =AL69*U69 -> 81.223249 | AN69: 135079.41 | AO69: =AH69*AI69 -> 43225.411 | AP69: =U69+AB69 -> 0.7 | AQ69: =AL69*AP69/(AG69+AE69) -> 2.1060363
A70: MAP108 | B70: RESIDENCIAL CIDADE JARDIM I - CÁCERES | C70: https://earth.google.com/web/search/C%c3%81CERES/@-16.11433068,-57.66517767,145.36941085a,5953.03993857d,35y,-0h,0t,0r/data=CiwiJgokCQX_JH53NS3AETlJC9e-RS3AGdinZMrzwEzAIeq1E4h_yUzAQgIIAToDCgEwQgIIAEoICJfn8a8FEAA?authuser=0 | D70: 1 | E70: LandBank | G70: 1865 | J70: 336 | K70: OESTE | L70: CÁCERES | M70: MT | N70: RESIDENCIAL CIDADE JARDIM I | O70: Parceria | P70: 0 | Q70: Loteamento | R70: Sim | S70: 2026 | T70: 46295 | U70: 0.81 | V70: 0.19 | W70: =SUM(U70:V70) -> 1 | X70: 0.05 | Y70: 0 | Z70: 0.068 | AA70: 0.198 | AC70: 169349 | AE70: =P70/10^6 -> 0 | AF70: =IF(AL70=0,0,AE70/AL70) -> 0 | AG70: =(AH70*AI70*AJ70)/10^6 -> 22.5036 | AH70: 133 | AI70: 235 | AJ70: 720 | AK70: 450 | AL70: =(AK70*AJ70*AI70)/10^6 -> 76.14 | AM70: =AL70*U70 -> 61.6734 | AN70: 90000 | AO70: =AH70*AI70 -> 31255 | AP70: =U70+AB70 -> 0.81 | AQ70: =AL70*AP70/(AG70+AE70) -> 2.7406015
A71: MAP108 | B71: RESIDENCIAL CIDADE JARDIM I - STP2 - CÁCERES | C71: https://earth.google.com/web/search/C%c3%81CERES/@-16.11433068,-57.66517767,145.36941085a,5953.03993857d,35y,-0h,0t,0r/data=CiwiJgokCQX_JH53NS3AETlJC9e-RS3AGdinZMrzwEzAIeq1E4h_yUzAQgIIAToDCgEwQgIIAEoICJfn8a8FEAA?authuser=0 | D71: 1 | E71: LandBank | G71: 1865 | J71: 337 | K71: OESTE | L71: CÁCERES | M71: MT | N71: RESIDENCIAL CIDADE JARDIM I - STP2 | O71: Parceria | P71: 0 | Q71: Loteamento | R71: Sim | S71: 2027 | T71: 46660 | U71: 0.81 | V71: 0.19 | W71: =SUM(U71:V71) -> 1 | X71: 0.05 | Y71: 0 | Z71: 0.068 | AA71: 0.198 | AC71: 169349 | AE71: =P71/10^6 -> 0 | AF71: =IF(AL71=0,0,AE71/AL71) -> 0 | AG71: =(AH71*AI71*AJ71)/10^6 -> 22.567972 | AH71: 133 | AI71: 236 | AJ71: 719 | AK71: 450 | AL71: =(AK71*AJ71*AI71)/10^6 -> 76.3578 | AM71: =AL71*U71 -> 61.849818 | AN71: 90000 | AO71: =AH71*AI71 -> 31388 | AP71: =U71+AB71 -> 0.81 | AQ71: =AL71*AP71/(AG71+AE71) -> 2.7406015
A72: MAP109 | B72: RESIDENCIAL CIDADE JARDIM II - CÁCERES | C72: https://earth.google.com/web/search/C%c3%81CERES/@-16.11433068,-57.66517767,145.36941085a,5953.03993857d,35y,-0h,0t,0r/data=CiwiJgokCQX_JH53NS3AETlJC9e-RS3AGdinZMrzwEzAIeq1E4h_yUzAQgIIAToDCgEwQgIIAEoICJfn8a8FEAA?authuser=0 | D72: 1 | E72: LandBank | G72: 1865 | J72: 338 | K72: OESTE | L72: CÁCERES | M72: MT | N72: RESIDENCIAL CIDADE JARDIM II | O72: Parceria | P72: 0 | Q72: Loteamento | R72: Sim | S72: 2029 | T72: 47391 | U72: 0.81 | V72: 0.19 | W72: =SUM(U72:V72) -> 1 | X72: 0.05 | Y72: 0 | Z72: 0.068 | AA72: 0.198 | AC72: 240277 | AE72: =P72/10^6 -> 0 | AF72: =IF(AL72=0,0,AE72/AL72) -> 0 | AG72: =(AH72*AI72*AJ72)/10^6 -> 32.0264 | AH72: 133 | AI72: 215 | AJ72: 1120 | AK72: 450 | AL72: =(AK72*AJ72*AI72)/10^6 -> 108.36 | AM72: =AL72*U72 -> 87.7716 | AN72: 90000 | AO72: =AH72*AI72 -> 28595 | AP72: =U72+AB72 -> 0.81 | AQ72: =AL72*AP72/(AG72+AE72) -> 2.7406015
A73: MAP110 | B73: RESIDENCIAL CIDADE JARDIM III - CÁCERES | C73: https://earth.google.com/web/search/C%c3%81CERES/@-16.11433068,-57.66517767,145.36941085a,5953.03993857d,35y,-0h,0t,0r/data=CiwiJgokCQX_JH53NS3AETlJC9e-RS3AGdinZMrzwEzAIeq1E4h_yUzAQgIIAToDCgEwQgIIAEoICJfn8a8FEAA?authuser=0 | D73: 1 | E73: LandBank | G73: 1865 | J73: 339 | K73: OESTE | L73: CÁCERES | M73: MT | N73: RESIDENCIAL CIDADE JARDIM III | O73: Parceria | P73: 0 | Q73: Loteamento | R73: - | S73: 2031 | T73: 48121 | U73: 0.81 | V73: 0.19 | W73: =SUM(U73:V73) -> 1 | X73: 0.05 | Y73: 0 | Z73: 0.068 | AA73: 0.198 | AC73: =AI73*AJ73 -> 296270 | AE73: =P73/10^6 -> 0 | AF73: =IF(AL73=0,0,AE73/AL73) -> 0 | AG73: =(AH73*AI73*AJ73)/10^6 -> 39.40391 | AH73: 133 | AI73: 215 | AJ73: 1378 | AK73: 477.27 | AL73: =(AK73*AJ73*AI73)/10^6 -> 141.40078 | AM73: =AL73*U73 -> 114.53463 | AN73: 104999.4 | AO73: =AH73*AI73 -> 28595 | AP73: =U73+AB73 -> 0.81 | AQ73: =AL73*AP73/(AG73+AE73) -> 2.906682
A74: MAP111 | B74: RESIDENCIAL CIDADE JARDIM I - TANGARÁ DA SERRA | C74: https://earth.google.com/web/search/TANGAR%c3%81+DA+SERRA/@-14.62032689,-57.54082084,346.92096178a,5258.20888551d,35y,0h,0t,0r/data=CiwiJgokCXA9rQptMS_AEXKWStZFPy_AGehdnQKoD0zAIeamtZ71FkzAQgIIAToDCgEwQgIIAEoICJfn8a8FEAA?authuser=0 | D74: 1 | E74: LandBank | G74: 2107 | J74: 340 | K74: OESTE | L74: TANGARÁ DA SERRA | M74: MT | N74: RESIDENCIAL CIDADE JARDIM I | O74: Compra e Venda | P74: 10682.93 | Q74: Loteamento | R74: Sim | S74: 2028 | T74: 47118 | U74: 0.7 | V74: 0.3 | W74: =SUM(U74:V74) -> 1 | X74: 0.05 | Y74: 0.09 | Z74: 0.068 | AA74: 0.198 | AC74: =AI74*AJ74 -> 280040.63 | AE74: =P74/10^6 -> 0.01068293 | AF74: =IF(AL74=0,0,AE74/AL74) -> 7.6295572e-05 | AG74: =(AH74*AI74*AJ74)/10^6 -> 37.245404 | AH74: 133 | AI74: 324.1211 | AJ74: 864 | AK74: 500 | AL74: =(AK74*AJ74*AI74)/10^6 -> 140.02032 | AM74: =AL74*U74 -> 98.014221 | AN74: 134980.96 | AO74: =AH74*AI74 -> 43108.106 | AP74: =U74+AB74 -> 0.7 | AQ74: =AL74*AP74/(AG74+AE74) -> 2.6308244
A75: MAP111 | B75: RESIDENCIAL CIDADE JARDIM I - STP2 - TANGARÁ DA SERRA | C75: https://earth.google.com/web/search/TANGAR%c3%81+DA+SERRA/@-14.62032689,-57.54082084,346.92096178a,5258.20888551d,35y,0h,0t,0r/data=CiwiJgokCXA9rQptMS_AEXKWStZFPy_AGehdnQKoD0zAIeamtZ71FkzAQgIIAToDCgEwQgIIAEoICJfn8a8FEAA?authuser=0 | D75: 1 | E75: LandBank | G75: 2107 | J75: 341 | K75: OESTE | L75: TANGARÁ DA SERRA | M75: MT | N75: RESIDENCIAL CIDADE JARDIM I - STP2 | O75: Compra e Venda | P75: 10682.93 | Q75: Loteamento | R75: Sim | S75: 2029 | T75: 47483 | U75: 0.7 | V75: 0.3 | W75: =SUM(U75:V75) -> 1 | X75: 0.05 | Y75: 0.09 | Z75: 0.068 | AA75: 0.198 | AC75: =AI75*AJ75 -> 279716.51 | AE75: =P75/10^6 -> 0.01068293 | AF75: =IF(AL75=0,0,AE75/AL75) -> 7.6383979e-05 | AG75: =(AH75*AI75*AJ75)/10^6 -> 37.202296 | AH75: 133 | AI75: 324.1211 | AJ75: 863 | AK75: 500 | AL75: =(AK75*AJ75*AI75)/10^6 -> 139.85825 | AM75: =AL75*U75 -> 97.900778 | AN75: 135128.16 | AO75: =AH75*AI75 -> 43108.106 | AP75: =U75+AB75 -> 0.7 | AQ75: =AL75*AP75/(AG75+AE75) -> 2.6308235
A76: MAP112 | B76: RESIDENCIAL CIDADE JARDIM II - TANGARÁ DA SERRA | C76: https://earth.google.com/web/search/TANGAR%c3%81+DA+SERRA/@-14.62032689,-57.54082084,346.92096178a,5258.20888551d,35y,0h,0t,0r/data=CiwiJgokCXA9rQptMS_AEXKWStZFPy_AGehdnQKoD0zAIeamtZ71FkzAQgIIAToDCgEwQgIIAEoICJfn8a8FEAA?authuser=0 | D76: 1 | E76: LandBank | G76: 2107 | J76: 342 | K76: OESTE | L76: TANGARÁ DA SERRA | M76: MT | N76: RESIDENCIAL CIDADE JARDIM II | O76: Compra e Venda | P76: 10682.93 | Q76: Loteamento | R76: - | S76: 2030 | T76: 47848 | U76: 0.7 | V76: 0.3 | W76: =SUM(U76:V76) -> 1 | X76: 0.05 | Y76: 0.09 | Z76: 0.068 | AA76: 0.198 | AC76: =AI76*AJ76 -> 240799.25 | AE76: =P76/10^6 -> 0.01068293 | AF76: =IF(AL76=0,0,AE76/AL76) -> 8.8728931e-05 | AG76: =(AH76*AI76*AJ76)/10^6 -> 32.0263 | AH76: 133 | AI76: 264.90566 | AJ76: 909 | AK76: 500 | AL76: =(AK76*AJ76*AI76)/10^6 -> 120.39962 | AM76: =AL76*U76 -> 84.279737 | AN76: 132452.83 | AO76: =AH76*AI76 -> 35232.453 | AP76: =U76+AB76 -> 0.7 | AQ76: =AL76*AP76/(AG76+AE76) -> 2.6307014
A77: MAP112 | B77: RESIDENCIAL CIDADE JARDIM II - STP 2 - TANGARÁ DA SERRA | C77: https://earth.google.com/web/search/TANGAR%c3%81+DA+SERRA/@-14.62032689,-57.54082084,346.92096178a,5258.20888551d,35y,0h,0t,0r/data=CiwiJgokCXA9rQptMS_AEXKWStZFPy_AGehdnQKoD0zAIeamtZ71FkzAQgIIAToDCgEwQgIIAEoICJfn8a8FEAA?authuser=0 | D77: 1 | E77: LandBank | G77: 2107 | J77: 343 | K77: OESTE | L77: TANGARÁ DA SERRA | M77: MT | N77: RESIDENCIAL CIDADE JARDIM II - STP 2 | O77: Compra e Venda | P77: 10682.93 | Q77: Loteamento | R77: - | S77: 2031 | T77: 48213 | U77: 0.7 | V77: 0.3 | W77: =SUM(U77:V77) -> 1 | X77: 0.05 | Y77: 0.09 | Z77: 0.068 | AA77: 0.198 | AC77: =AI77*AJ77 -> 240799.25 | AE77: =P77/10^6 -> 0.01068293 | AF77: =IF(AL77=0,0,AE77/AL77) -> 8.8728931e-05 | AG77: =(AH77*AI77*AJ77)/10^6 -> 32.0263 | AH77: 133 | AI77: 265.19741 | AJ77: 908 | AK77: 500 | AL77: =(AK77*AJ77*AI77)/10^6 -> 120.39962 | AM77: =AL77*U77 -> 84.279737 | AN77: 132598.71 | AO77: =AH77*AI77 -> 35271.256 | AP77: =U77+AB77 -> 0.7 | AQ77: =AL77*AP77/(AG77+AE77) -> 2.6307014
A78: MAP112 | B78: RESIDENCIAL CIDADE JARDIM III - TANGARÁ DA SERRA | C78: https://earth.google.com/web/search/TANGAR%c3%81+DA+SERRA/@-14.62032689,-57.54082084,346.92096178a,5258.20888551d,35y,0h,0t,0r/data=CiwiJgokCXA9rQptMS_AEXKWStZFPy_AGehdnQKoD0zAIeamtZ71FkzAQgIIAToDCgEwQgIIAEoICJfn8a8FEAA?authuser=0 | D78: 1 | E78: LandBank | G78: 2107 | J78: 344 | K78: OESTE | L78: TANGARÁ DA SERRA | M78: MT | N78: RESIDENCIAL CIDADE JARDIM III | O78: Compra e Venda | P78: 10682.93 | Q78: Loteamento | R78: - | S78: 2032 | T78: 48579 | U78: 0.7 | V78: 0.3 | W78: =SUM(U78:V78) -> 1 | X78: 0.05 | Y78: 0.09 | Z78: 0.068 | AA78: 0.198 | AC78: =AI78*AJ78 -> 365843.31 | AE78: =P78/10^6 -> 0.01068293 | AF78: =IF(AL78=0,0,AE78/AL78) -> 5.8401669e-05 | AG78: =(AH78*AI78*AJ78)/10^6 -> 48.65716 | AH78: 133 | AI78: 263.7659 | AJ78: 1387 | AK78: 500 | AL78: =(AK78*AJ78*AI78)/10^6 -> 182.92165 | AM78: =AL78*U78 -> 128.04516 | AN78: 131882.95 | AO78: =AH78*AI78 -> 35080.865 | AP78: =U78+AB78 -> 0.7 | AQ78: =AL78*AP78/(AG78+AE78) -> 2.6310013
A79: MAP112 | B79: RESIDENCIAL CIDADE JARDIM IV - TANGARÁ DA SERRA | C79: https://earth.google.com/web/search/TANGAR%c3%81+DA+SERRA/@-14.62032689,-57.54082084,346.92096178a,5258.20888551d,35y,0h,0t,0r/data=CiwiJgokCXA9rQptMS_AEXKWStZFPy_AGehdnQKoD0zAIeamtZ71FkzAQgIIAToDCgEwQgIIAEoICJfn8a8FEAA?authuser=0 | D79: 1 | E79: LandBank | G79: 2107 | J79: 345 | K79: OESTE | L79: TANGARÁ DA SERRA | M79: MT | N79: RESIDENCIAL CIDADE JARDIM IV | O79: Compra e Venda | P79: 10682.93 | Q79: Loteamento | R79: - | S79: 2034 | T79: 49309 | U79: 0.7 | V79: 0.3 | W79: =SUM(U79:V79) -> 1 | X79: 0.05 | Y79: 0.09 | Z79: 0.068 | AA79: 0.198 | AC79: =AI79*AJ79 -> 252026.52 | AE79: =P79/10^6 -> 0.01068293 | AF79: =IF(AL79=0,0,AE79/AL79) -> 8.4776237e-05 | AG79: =(AH79*AI79*AJ79)/10^6 -> 33.519527 | AH79: 133 | AI79: 259.02006 | AJ79: 973 | AK79: 500 | AL79: =(AK79*AJ79*AI79)/10^6 -> 126.01326 | AM79: =AL79*U79 -> 88.209282 | AN79: 129510.03 | AO79: =AH79*AI79 -> 34449.668 | AP79: =U79+AB79 -> 0.7 | AQ79: =AL79*AP79/(AG79+AE79) -> 2.6307405
A80: MAP113 | B80: BURITI GARDEN PRIME II - VARZEA GRANDE | C80: https://earth.google.com/web/search/CUIAB%c3%81/@-15.61005921,-56.15084275,175.93804739a,4592.0123658d,35y,0h,0t,0r/data=CiwiJgokCTDbVLh45ybAEXD1A07O7ybAGaZZUBA5uU7AIdT4-d2KvU7AQgIIAToDCgEwQgIIAEoICJfn8a8FEAA?authuser=0 | D80: 1 | E80: LandBank | G80: 1930 | J80: 347 | K80: OESTE | L80: VARZEA GRANDE | M80: MT | N80: BURITI GARDEN PRIME II | O80: Parceria | P80: 0 | Q80: Condominio | R80: - | S80: 2029 | T80: 47299 | U80: 0.7 | V80: 0.3 | W80: =SUM(U80:V80) -> 1 | X80: 0.05 | Y80: 0.09 | Z80: 0.068 | AA80: 0.198 | AC80: =AI80*AJ80 -> 117260 | AE80: =P80/10^6 -> 0 | AF80: =IF(AL80=0,0,AE80/AL80) -> 0 | AG80: =(AH80*AI80*AJ80)/10^6 -> 30.4876 | AH80: 260 | AI80: 220 | AJ80: 533 | AK80: 1200 | AL80: =(AK80*AJ80*AI80)/10^6 -> 140.712 | AM80: =AL80*U80 -> 98.4984 | AN80: 264000 | AO80: =AH80*AI80 -> 57200 | AP80: =U80+AB80 -> 0.7 | AQ80: =AL80*AP80/(AG80+AE80) -> 3.2307692
A81: MAP114 | B81: BURITI GARDEN PRIME III - VARZEA GRANDE | C81: https://earth.google.com/web/search/CUIAB%c3%81/@-15.61005921,-56.15084275,175.93804739a,4592.0123658d,35y,0h,0t,0r/data=CiwiJgokCTDbVLh45ybAEXD1A07O7ybAGaZZUBA5uU7AIdT4-d2KvU7AQgIIAToDCgEwQgIIAEoICJfn8a8FEAA?authuser=0 | D81: 1 | E81: LandBank | G81: 1930 | J81: 348 | K81: OESTE | L81: VARZEA GRANDE | M81: MT | N81: BURITI GARDEN PRIME III | O81: Parceria | P81: 0 | Q81: Condominio | R81: - | S81: 2028 | T81: 46934 | U81: 0.7 | V81: 0.3 | W81: =SUM(U81:V81) -> 1 | X81: 0.05 | Y81: 0.09 | Z81: 0.068 | AA81: 0.198 | AC81: =AI81*AJ81 -> 121000 | AE81: =P81/10^6 -> 0 | AF81: =IF(AL81=0,0,AE81/AL81) -> 0 | AG81: =(AH81*AI81*AJ81)/10^6 -> 31.46 | AH81: 260 | AI81: 360.11905 | AJ81: 336 | AK81: 1200 | AL81: =(AK81*AJ81*AI81)/10^6 -> 145.2 | AM81: =AL81*U81 -> 101.64 | AN81: 432142.86 | AO81: =AH81*AI81 -> 93630.952 | AP81: =U81+AB81 -> 0.7 | AQ81: =AL81*AP81/(AG81+AE81) -> 3.2307692
A82: MAP127 | B82: SPE BTMV EMPREENDIMENTOS IMOBILIARIOS LTDA | D82: 1 | E82: LandBank | G82: 1929 | K82: OESTE | L82: VARZEA GRANDE | M82: MT | N82: SPE BTMV EMPREENDIMENTOS IMOBILIARIOS LTDA | O82: Parceria | P82: 0 | Q82: Condominio | R82: - | U82: 0.7 | V82: 0.3 | W82: =SUM(U82:V82) -> 1 | AA82: 0.198 | AC82: =AI82*AJ82 -> 238260 | AE82: =P82/10^6 -> 0 | AF82: =IF(AL82=0,0,AE82/AL82) -> 0 | AG82: =(AH82*AI82*AJ82)/10^6 -> 71.478 | AH82: 300 | AI82: 220 | AJ82: 1083 | AK82: 1500 | AL82: =(AK82*AJ82*AI82)/10^6 -> 357.39 | AM82: =AL82*U82 -> 250.173 | AN82: 330000 | AO82: =AH82*AI82 -> 66000 | AP82: =U82+AB82 -> 0.7 | AQ82: =AL82*AP82/(AG82+AE82) -> 3.5
A83: MAP115 | B83: BURITI GARDEN PREMIUM - CUIABÁ | C83: https://earth.google.com/web/search/CUIAB%c3%81/@-15.55669308,-56.14650334,159.69800373a,2841.75984399d,35y,0h,0t,0r/data=CiwiJgokCTDbVLh45ybAEXD1A07O7ybAGaZZUBA5uU7AIdT4-d2KvU7AQgIIAToDCgEwQgIIAEoICJfn8a8FEAA?authuser=0 | D83: 1 | E83: LandBank | G83: 2100 | J83: 349 | K83: OESTE | L83: CUIABÁ | M83: MT | N83: BURITI GARDEN PREMIUM | O83: Parceria | P83: 0 | Q83: Condominio | R83: - | S83: 2027 | T83: 46660 | U83: 0.65 | V83: 0.35 | W83: =SUM(U83:V83) -> 1 | X83: 0.05 | Y83: 0 | Z83: 0.068 | AA83: 0.198 | AC83: =AI83*AJ83 -> 300776 | AE83: =P83/10^6 -> 0 | AF83: =IF(AL83=0,0,AE83/AL83) -> 0 | AG83: =(AH83*AI83*AJ83)/10^6 -> 96.24832 | AH83: 320 | AI83: 360.21078 | AJ83: 835 | AK83: 1500 | AL83: =(AK83*AJ83*AI83)/10^6 -> 451.164 | AM83: =AL83*U83 -> 293.2566 | AN83: 720000 | AO83: =AH83*AI83 -> 115267.45 | AP83: =U83+AB83 -> 0.65 | AQ83: =AL83*AP83/(AG83+AE83) -> 3.046875
A84: MAP116 | B84: PARK DOS BURITIS II - CACOAL | C84: https://earth.google.com/web/search/CACOAL/@-11.46023209,-61.46392704,192.80524441a,2677.20500742d,35y,0.00000001h,0t,0r/data=CiwiJgokCR-NyuOUryXAEUa9h2WxuCXAGViFzbpE_U7AISHjgBr7AU_AQgIIAToDCgEwQgIIAEoICJfn8a8FEAA?authuser=0 | D84: 1 | E84: LandBank | G84: 2102 | J84: 350 | K84: OESTE | L84: CACOAL | M84: RO | N84: PARK DOS BURITIS II | O84: Parceria | P84: 0 | Q84: Loteamento | R84: Sim | S84: 2026 | T84: 46387 | U84: 0.7 | V84: 0.3 | W84: =SUM(U84:V84) -> 1 | X84: 0.05 | Y84: 0.09 | Z84: 0.068 | AA84: 0.198 | AC84: 226990.07 | AE84: =P84/10^6 -> 0 | AF84: =IF(AL84=0,0,AE84/AL84) -> 0 | AG84: =(AH84*AI84*AJ84)/10^6 -> 30.146445 | AH84: 133 | AI84: 219 | AJ84: 1035 | AK84: 477.27 | AL84: =(AK84*AJ84*AI84)/10^6 -> 108.1804 | AM84: =AL84*U84 -> 75.726283 | AN84: 104999.4 | AO84: =AH84*AI84 -> 29127 | AP84: =U84+AB84 -> 0.7 | AQ84: =AL84*AP84/(AG84+AE84) -> 2.5119474
A85: MAP117 | B85: RESIDENCIAL JARDIM AMERICA - JI-PARANÁ | C85: https://earth.google.com/web/search/JI-PARAN%c3%81/@-10.85183117,-61.99706777,185.54123939a,2952.01716751d,35y,-0h,0t,0r/data=CnkaSxJFCiUweDkzYzk5YjAzNTkwN2UyYWY6MHgyZDY5YWM1MGU1ZTk5ZTUzGY33mWmxviXAIQ_23PjJ-k7AKgpKSS1QQVJBTsOBGAEgASImCiQJElfJHm5hJ8ARBtuZb2drJ8AZwJelwkDiTsAhv9JgP23nTsBCAggBOgMKATBCAggASggIl-fxrwUQAA?authuser=0 | D85: 1 | E85: LandBank | G85: 1989 | J85: 351 | K85: OESTE | L85: JI-PARANÁ | M85: RO | N85: RESIDENCIAL JARDIM AMERICA | O85: Parceria | P85: 0 | Q85: Loteamento | R85: Sim | S85: 2027 | T85: 46660 | U85: 0.74 | V85: 0.26 | W85: =SUM(U85:V85) -> 1 | X85: 0.05 | Y85: 0.05 | Z85: 0.068 | AA85: 0.198 | AC85: 122152 | AE85: =P85/10^6 -> 0 | AF85: =IF(AL85=0,0,AE85/AL85) -> 0 | AG85: =(AH85*AI85*AJ85)/10^6 -> 16.265634 | AH85: 133 | AI85: 218 | AJ85: 561 | AK85: 457.14 | AL85: =(AK85*AJ85*AI85)/10^6 -> 55.907308 | AM85: =AL85*U85 -> 41.371408 | AN85: 79999.5 | AO85: =AH85*AI85 -> 28994 | AP85: =U85+AB85 -> 0.74 | AQ85: =AL85*AP85/(AG85+AE85) -> 2.5434857
A86: MAP118 | B86: RESIDENCIAL CIDADE JARDIM II - ROLIM DE MOURA | C86: https://earth.google.com/web/search/ROLIM+DE+MOURA/@-11.70003411,-61.7878114,251.9337313a,3182.60368671d,35y,0h,0t,0r/data=CnwaThJICiQweDkzYzg2YmYyMDQ1MWZkNDc6MHg4MjlmMWM5MmZjMTJiNGQZjYZCuo5zJ8AhCpf6HprjTsAqDlJPTElNIERFIE1PVVJBGAEgASImCiQJU-hXLybDI8ARtbsCkK3JI8AZWYZJdKGGT8Ah1B97Of-JT8BCAggBOgMKATBCAggASggIl-fxrwUQAA?authuser=0 | D86: 1 | E86: LandBank | G86: 2000 | J86: 352 | K86: OESTE | L86: ROLIM DE MOURA | M86: RO | N86: RESIDENCIAL CIDADE JARDIM II | O86: Compra e Venda | P86: 250000 | Q86: Loteamento | R86: Sim | S86: 2027 | T86: 46568 | U86: 0.7 | V86: 0.3 | W86: =SUM(U86:V86) -> 1 | X86: 0.05 | Y86: 0.05 | Z86: 0.068 | AA86: 0.198 | AC86: 310438 | AE86: =P86/10^6 -> 0.25 | AF86: =IF(AL86=0,0,AE86/AL86) -> 0.0019716358 | AG86: =(AH86*AI86*AJ86)/10^6 -> 41.223616 | AH86: 133 | AI86: 232 | AJ86: 1336 | AK86: 409.09 | AL86: =(AK86*AJ86*AI86)/10^6 -> 126.79826 | AM86: =AL86*U86 -> 88.758785 | AN86: 89999.8 | AO86: =AH86*AI86 -> 30856 | AP86: =U86+AB86 -> 0.7 | AQ86: =AL86*AP86/(AG86+AE86) -> 2.1401265
A87: MAP119 | B87: RESIDENCIAL CIDADE JARDIM IIII - ROLIM DE MOURA | C87: https://earth.google.com/web/search/ROLIM+DE+MOURA/@-11.70003411,-61.7878114,251.9337313a,3182.60368671d,35y,0h,0t,0r/data=CnwaThJICiQweDkzYzg2YmYyMDQ1MWZkNDc6MHg4MjlmMWM5MmZjMTJiNGQZjYZCuo5zJ8AhCpf6HprjTsAqDlJPTElNIERFIE1PVVJBGAEgASImCiQJU-hXLybDI8ARtbsCkK3JI8AZWYZJdKGGT8Ah1B97Of-JT8BCAggBOgMKATBCAggASggIl-fxrwUQAA?authuser=0 | D87: 1 | E87: LandBank | G87: 2108 | J87: 353 | K87: OESTE | L87: ROLIM DE MOURA | M87: RO | N87: RESIDENCIAL CIDADE JARDIM IIII | O87: Compra e Venda | P87: 250000 | Q87: Loteamento | R87: - | S87: 2028 | T87: 46934 | U87: 0.7 | V87: 0.3 | W87: =SUM(U87:V87) -> 1 | X87: 0.05 | Y87: 0.05 | Z87: 0.068 | AA87: 0.198 | AC87: =AI87*AJ87 -> 69757.27 | AE87: =P87/10^6 -> 0.25 | AF87: =IF(AL87=0,0,AE87/AL87) -> 0.0083345485 | AG87: =(AH87*AI87*AJ87)/10^6 -> 9.2777169 | AH87: 133 | AI87: 255.52114 | AJ87: 273 | AK87: 430 | AL87: =(AK87*AJ87*AI87)/10^6 -> 29.995626 | AM87: =AL87*U87 -> 20.996938 | AN87: 109874.09 | AO87: =AH87*AI87 -> 33984.311 | AP87: =U87+AB87 -> 0.7 | AQ87: =AL87*AP87/(AG87+AE87) -> 2.2037744
A88: MAP120 | B88: RESIDENCIAL CIDADE JARDIM III - ARIQUEMES | C88: https://earth.google.com/web/search/ARIQUEMES/@-9.88752676,-63.06495176,110.43672402a,2137.88748754d,35y,0h,0t,0r/data=CngaShJECiUweDkzY2M4ZmY5NTkwYWU4OTc6MHg0OTM5OGYxNTllOGY5YmEzGQOoTqz4zyPAIejEeZM6hE_AKglBUklRVUVNRVMYASABIiYKJAn0V4MWyvIwwBExfXARXvkwwBmukrOFkXVIwCHsK48mjnxIwEICCAE6AwoBMEICCABKCAiX5_GvBRAA?authuser=0 | D88: 1 | E88: LandBank | G88: 2104 | J88: 354 | K88: OESTE | L88: ARIQUEMES | M88: RO | N88: RESIDENCIAL CIDADE JARDIM III | O88: Compra e Venda | P88: 1057142.9 | Q88: Loteamento | R88: Sim | S88: 2028 | T88: 47026 | U88: 0.7 | V88: 0.3 | W88: =SUM(U88:V88) -> 1 | X88: 0.05 | Y88: 0.09 | Z88: 0.068 | AA88: 0.198 | AC88: =AI88*AJ88 -> 593922 | AE88: =P88/10^6 -> 1.0571429 | AF88: =IF(AL88=0,0,AE88/AL88) -> 0 | AG88: =(AH88*AI88*AJ88)/10^6 -> 78.991626 | AH88: 133 | AI88: 237 | AJ88: 2506 | AK88: 0 | AL88: =(AK88*AJ88*AI88)/10^6 -> 0 | AM88: =AL88*U88 -> 0 | AN88: 0 | AO88: =AH88*AI88 -> 31521 | AP88: =U88+AB88 -> 0.7 | AQ88: =AL88*AP88/(AG88+AE88) -> 0
A89: MAP126 | B89: RESIDENCIAL PARQUE JARDIM | D89: 1 | E89: LandBank | G89: 2588 | K89: OESTE | L89: TANGARÁ DA SERRA | M89: MT | N89: RESIDENCIAL PARQUE JARDIM | O89: Compra e Venda | P89: 10682.93 | Q89: Loteamento | R89: - | U89: 0.7 | V89: 0.3 | W89: =SUM(U89:V89) -> 1 | AA89: 0.198 | AC89: =AI89*AJ89 -> 561000 | AE89: =P89/10^6 -> 0.01068293 | AF89: =IF(AL89=0,0,AE89/AL89) -> 4.760664e-05 | AG89: =(AH89*AI89*AJ89)/10^6 -> 74.613 | AH89: 133 | AI89: 250 | AJ89: 2244 | AK89: 400 | AL89: =(AK89*AJ89*AI89)/10^6 -> 224.4 | AM89: =AL89*U89 -> 157.08 | AN89: 100000 | AO89: =AH89*AI89 -> 33250 | AP89: =U89+AB89 -> 0.7 | AQ89: =AL89*AP89/(AG89+AE89) -> 2.1049618
A90: MAP128 | B90: HONORATO PIRES MIRANDA "ESPÓLIO" | D90: 1 | E90: LandBank | G90: 2101 | K90: OESTE | L90: VARZEA GRANDE | M90: MT | N90: A DEFINIR | O90: Parceria | P90: 0 | Q90: Condominio | R90: - | U90: 0.7 | V90: 0.3 | W90: =SUM(U90:V90) -> 1 | AA90: 0.198 | AC90: =AI90*AJ90 -> 139700 | AE90: =P90/10^6 -> 0 | AF90: =IF(AL90=0,0,AE90/AL90) -> 0 | AG90: =(AH90*AI90*AJ90)/10^6 -> 41.91 | AH90: 300 | AI90: 220 | AJ90: 635 | AK90: 1500 | AL90: =(AK90*AJ90*AI90)/10^6 -> 209.55 | AM90: =AL90*U90 -> 146.685 | AN90: 330000 | AO90: =AH90*AI90 -> 66000 | AP90: =U90+AB90 -> 0.7 | AQ90: =AL90*AP90/(AG90+AE90) -> 3.5
A91: MAP130 | B91: CHAPADA DOS GUIMARÃES-LAGO DO MANSO | D91: 1 | E91: Estudo de viabilidade | G91: 2645 | K91: OESTE | L91: CHAPADA DOS GUIMARÃES | M91: MT | N91: A DEFINIR | O91: Parceria | P91: 0 | Q91: Loteamento | R91: - | U91: 0.8 | V91: 0.2 | W91: =SUM(U91:V91) -> 1 | AA91: 0.198 | AC91: =AI91*AJ91 -> 1500200 | AE91: =P91/10^6 -> 0 | AF91: =IF(AL91=0,0,AE91/AL91) -> 0 | AG91: =(AH91*AI91*AJ91)/10^6 -> 199.5266 | AH91: 133 | AI91: 1300 | AJ91: 1154 | AK91: 1400 | AL91: =(AK91*AJ91*AI91)/10^6 -> 2100.28 | AM91: =AL91*U91 -> 1680.224 | AN91: 1820000 | AO91: =AH91*AI91 -> 172900 | AP91: =U91+AB91 -> 0.8 | AQ91: =AL91*AP91/(AG91+AE91) -> 8.4210526
A92: MAP131 | B92: ZEZO MALOUF | D92: 1 | E92: Estudo de viabilidade | G92: 1890 | K92: OESTE | L92: CUIABÁ | M92: MT | N92: A DEFINIR | O92: Parceria | P92: 0 | Q92: Loteamento | R92: - | U92: 0.72 | V92: 0.28 | W92: =SUM(U92:V92) -> 1 | AA92: 0.198 | AC92: =AI92*AJ92 -> 2007600 | AE92: =P92/10^6 -> 0 | AF92: =IF(AL92=0,0,AE92/AL92) -> 0 | AG92: =(AH92*AI92*AJ92)/10^6 -> 267.0108 | AH92: 133 | AI92: 200 | AJ92: 10038 | AK92: 550 | AL92: =(AK92*AJ92*AI92)/10^6 -> 1104.18 | AM92: =AL92*U92 -> 795.0096 | AN92: 110000 | AO92: =AH92*AI92 -> 26600 | AP92: =U92+AB92 -> 0.72 | AQ92: =AL92*AP92/(AG92+AE92) -> 2.9774436
A93: MAP135 | B93: MUNARO EMPREENDIMENTOS IMOBILIÁRIOS LTDA | D93: 1 | E93: Estudo de viabilidade | G93: 2767 | K93: OESTE | L93: GUARANTÃ DO NORTE | M93: MT | N93: A DEFINIR | O93: Parceria | P93: 0 | Q93: Loteamento | R93: - | S93: - | U93: 0.75 | V93: 0.25 | W93: =SUM(U93:V93) -> 1 | AA93: 0.198 | AC93: 780000 | AE93: =P93/10^6 -> 0 | AF93: =IF(AL93=0,0,AE93/AL93) -> 0 | AG93: =(AH93*AI93*AJ93)/10^6 -> 57.057 | AH93: 133 | AI93: 200 | AJ93: 2145 | AK93: 550 | AL93: =(AK93*AJ93*AI93)/10^6 -> 235.95 | AM93: =AL93*U93 -> 176.9625 | AN93: 110000 | AO93: =AH93*AI93 -> 26600 | AP93: =U93+AB93 -> 0.75 | AQ93: =AL93*AP93/(AG93+AE93) -> 3.1015038
A94: MAP136 | B94: PERGENTINO DE VASCONCELOS JUNIOR | D94: 1 | E94: Estudo de viabilidade | G94: 2726 | K94: SUDESTE | L94: COLATINA | M94: ES | N94: A DEFINIR | O94: Parceria | P94: 0 | Q94: Loteamento | R94: - | S94: - | U94: 0.67 | V94: 0.33 | W94: =SUM(U94:V94) -> 1 | AA94: 0.198 | AC94: 444727 | AE94: =P94/10^6 -> 0 | AF94: =IF(AL94=0,0,AE94/AL94) -> 0 | AG94: =(AH94*AI94*AJ94)/10^6 -> 0 | AI94: 250 | AJ94: 720 | AK94: 700 | AL94: =(AK94*AJ94*AI94)/10^6 -> 126 | AM94: =AL94*U94 -> 84.42 | AN94: 175000 | AO94: =AH94*AI94 -> 0 | AP94: =U94+AB94 -> 0.67 | AQ94: =AL94*AP94/(AG94+AE94) -> #DIV/0!
A95: MAP069 | B95: A DEFINIR - FERNANDOPOLIS | C95: https://earth.google.com/web/search/Fernand%c3%b3polis,+SP/@-20.28018739,-50.27505914,502.32219773a,2203.4530223d,35y,0h,0t,0r/data=CoEBGlMSTQolMHg5NDk3ZjYxY2I3ZDkzM2VkOjB4ZDE4MmY0ZTc4OTRmNzUxYhmJ3MKpxUg0wCEGFEWjlh9JwCoSRmVybmFuZMOzcG9saXMsIFNQGAEgASImCiQJgnysRFGlMMARwB6b_Yj8OMAZwQm5IOWMQ8Ah3LyfaYryTMBCAggBOgMKATBCAggASggIl-fxrwUQAA?authuser=0 | D95: 1 | E95: LandBank | G95: PENDENCIA | J95: 264 | K95: SUDESTE | L95: FERNANDOPOLIS | M95: SP | N95: A DEFINIR | O95: Parceria | P95: 0 | Q95: Loteamento | R95: - | S95: 2032 | T95: 48395 | U95: 0.7 | V95: 0.3 | W95: =SUM(U95:V95) -> 1 | X95: 0.05 | Y95: 0 | Z95: 0.068 | AA95: 0.198 | AC95: =AI95*AJ95 -> 167923 | AE95: =P95/10^6 -> 0 | AF95: =IF(AL95=0,0,AE95/AL95) -> 0 | AG95: =(AH95*AI95*AJ95)/10^6 -> 27.371449 | AH95: 163 | AI95: 203.29661 | AJ95: 826 | AK95: 600 | AL95: =(AK95*AJ95*AI95)/10^6 -> 100.7538 | AM95: =AL95*U95 -> 70.52766 | AN95: 121977.97 | AO95: =AH95*AI95 -> 33137.347 | AP95: =U95+AB95 -> 0.7 | AQ95: =AL95*AP95/(AG95+AE95) -> 2.5766871
A96: MAP057 | B96: RESIDENCIAL CIDADE JARDIM I - ITAPETININGA | C96: https://earth.google.com/web/search/ITAPETININGA/@-23.62618263,-48.09089394,643.86218986a,3111.8044646d,35y,0h,0t,0r/data=CiwiJgokCSTz4KZOwTbAEWUEDjqixTbAGTHHXZ3oi0bAId3jN-OskEbAQgIIAToDCgEwQgIIAEoICJfn8a8FEAA?authuser=0 | D96: 1 | E96: LandBank | G96: 2277 | J96: 240 | K96: SUDESTE | L96: ITAPETININGA | M96: SP | N96: RESIDENCIAL CIDADE JARDIM I | O96: Parceria | P96: 0 | Q96: Loteamento | R96: Sim | S96: 2029 | T96: 47482 | U96: 0.55 | V96: 0.40002 | W96: =SUM(U96:V96) -> 0.95002 | X96: 0.05 | Y96: 0.09 | Z96: 0.068 | AA96: 0.198 | AB96: 0.04998 | AC96: =AI96*AJ96 -> 218006.26 | AE96: =P96/10^6 -> 0 | AF96: =IF(AL96=0,0,AE96/AL96) -> 0 | AG96: =(AH96*AI96*AJ96)/10^6 -> 35.53502 | AH96: 163 | AI96: 227.32665 | AJ96: 959 | AK96: 550 | AL96: =(AK96*AJ96*AI96)/10^6 -> 119.90344 | AM96: =AL96*U96 -> 65.946894 | AN96: 125029.66 | AO96: =AH96*AI96 -> 37054.244 | AP96: =U96+AB96 -> 0.59998 | AQ96: =AL96*AP96/(AG96+AE96) -> 2.0244724
A97: MAP058 | B97: RESIDENCIAL CIDADE JARDIM II - ITAPETININGA | C97: https://earth.google.com/web/search/ITAPETININGA/@-23.62618263,-48.09089394,643.86218986a,3111.8044646d,35y,0h,0t,0r/data=CiwiJgokCSTz4KZOwTbAEWUEDjqixTbAGTHHXZ3oi0bAId3jN-OskEbAQgIIAToDCgEwQgIIAEoICJfn8a8FEAA?authuser=0 | D97: 1 | E97: LandBank | G97: 2277 | J97: 241 | K97: SUDESTE | L97: ITAPETININGA | M97: SP | N97: RESIDENCIAL CIDADE JARDIM II | O97: Parceria | P97: 0 | Q97: Loteamento | R97: Sim | S97: 2031 | T97: 48212 | U97: 0.55 | V97: 0.40002 | W97: =SUM(U97:V97) -> 0.95002 | X97: 0.05 | Y97: 0.09 | Z97: 0.068 | AA97: 0.198 | AB97: 0.04998 | AC97: =AI97*AJ97 -> 268822.81 | AE97: =P97/10^6 -> 0 | AF97: =IF(AL97=0,0,AE97/AL97) -> 0 | AG97: =(AH97*AI97*AJ97)/10^6 -> 43.818118 | AH97: 163 | AI97: 218.73296 | AJ97: 1229 | AK97: 550 | AL97: =(AK97*AJ97*AI97)/10^6 -> 147.85255 | AM97: =AL97*U97 -> 81.3189 | AN97: 120303.13 | AO97: =AH97*AI97 -> 35653.473 | AP97: =U97+AB97 -> 0.59998 | AQ97: =AL97*AP97/(AG97+AE97) -> 2.0244724
A98: MAP059 | B98: A DEFINIR I - ITAPETININGA | C98: https://earth.google.com/web/search/ITAPETININGA/@-23.60041566,-48.11054145,648.36741354a,7499.34108211d,35y,0h,0t,0r/data=CiwiJgokCSTz4KZOwTbAEWUEDjqixTbAGTHHXZ3oi0bAId3jN-OskEbAQgIIAToDCgEwQgIIAEoICJfn8a8FEAA?authuser=0 | D98: 1 | E98: LandBank | G98: 2277 | J98: 242 | K98: SUDESTE | L98: ITAPETININGA | M98: SP | N98: A DEFINIR I | O98: Parceria | P98: 0 | Q98: Loteamento | R98: - | S98: 2033 | T98: 48943 | U98: 0.55 | V98: 0.40002 | W98: =SUM(U98:V98) -> 0.95002 | X98: 0.05 | Y98: 0.09 | Z98: 0.068 | AA98: 0.198 | AB98: 0.04998 | AC98: =AI98*AJ98 -> 315000 | AE98: =P98/10^6 -> 0 | AF98: =IF(AL98=0,0,AE98/AL98) -> 0 | AG98: =(AH98*AI98*AJ98)/10^6 -> 51.345 | AH98: 163 | AI98: 210 | AJ98: 1500 | AK98: 550 | AL98: =(AK98*AJ98*AI98)/10^6 -> 173.25 | AM98: =AL98*U98 -> 95.2875 | AN98: 115500 | AO98: =AH98*AI98 -> 34230 | AP98: =U98+AB98 -> 0.59998 | AQ98: =AL98*AP98/(AG98+AE98) -> 2.0244724
A99: MAP059 | B99: A DEFINIR II - ITAPETININGA | C99: https://earth.google.com/web/search/ITAPETININGA/@-23.60041566,-48.11054145,648.36741354a,7499.34108211d,35y,0h,0t,0r/data=CiwiJgokCSTz4KZOwTbAEWUEDjqixTbAGTHHXZ3oi0bAId3jN-OskEbAQgIIAToDCgEwQgIIAEoICJfn8a8FEAA?authuser=0 | D99: 1 | E99: LandBank | G99: 2277 | J99: 243 | K99: SUDESTE | L99: ITAPETININGA | M99: SP | N99: A DEFINIR II | O99: Parceria | P99: 0 | Q99: Loteamento | R99: - | S99: 2035 | T99: 49673 | U99: 0.55 | V99: 0.40002 | W99: =SUM(U99:V99) -> 0.95002 | X99: 0.05 | Y99: 0.09 | Z99: 0.068 | AA99: 0.198 | AB99: 0.04998 | AC99: =AI99*AJ99 -> 315000 | AE99: =P99/10^6 -> 0 | AF99: =IF(AL99=0,0,AE99/AL99) -> 0 | AG99: =(AH99*AI99*AJ99)/10^6 -> 51.345 | AH99: 163 | AI99: 210 | AJ99: 1500 | AK99: 550 | AL99: =(AK99*AJ99*AI99)/10^6 -> 173.25 | AM99: =AL99*U99 -> 95.2875 | AN99: 115500 | AO99: =AH99*AI99 -> 34230 | AP99: =U99+AB99 -> 0.59998 | AQ99: =AL99*AP99/(AG99+AE99) -> 2.0244724
A100: MAP059 | B100: A DEFINIR III - ITAPETININGA | C100: https://earth.google.com/web/search/ITAPETININGA/@-23.60041566,-48.11054145,648.36741354a,7499.34108211d,35y,0h,0t,0r/data=CiwiJgokCSTz4KZOwTbAEWUEDjqixTbAGTHHXZ3oi0bAId3jN-OskEbAQgIIAToDCgEwQgIIAEoICJfn8a8FEAA?authuser=0 | D100: 1 | E100: LandBank | G100: 2277 | J100: 244 | K100: SUDESTE | L100: ITAPETININGA | M100: SP | N100: A DEFINIR III | O100: Parceria | P100: 0 | Q100: Loteamento | R100: - | S100: 2037 | T100: 50404 | U100: 0.55 | V100: 0.40002 | W100: =SUM(U100:V100) -> 0.95002 | X100: 0.05 | Y100: 0.09 | Z100: 0.068 | AA100: 0.198 | AB100: 0.04998 | AC100: =AI100*AJ100 -> 315000 | AE100: =P100/10^6 -> 0 | AF100: =IF(AL100=0,0,AE100/AL100) -> 0 | AG100: =(AH100*AI100*AJ100)/10^6 -> 51.345 | AH100: 163 | AI100: 210 | AJ100: 1500 | AK100: 550 | AL100: =(AK100*AJ100*AI100)/10^6 -> 173.25 | AM100: =AL100*U100 -> 95.2875 | AN100: 115500 | AO100: =AH100*AI100 -> 34230 | AP100: =U100+AB100 -> 0.59998 | AQ100: =AL100*AP100/(AG100+AE100) -> 2.0244724
...

Sheet Planilha2
G1: =COUNTA(_xlfn.ANCHORARRAY(G4)) -> 76 | H1: =COUNTA(_xlfn.ANCHORARRAY(H4)) -> 19
B2: Resumo Executivo | G2: =G1-1 -> 75 | H2: =H1-1 -> 18
G3: cidade | H3: uf
B4: Empreendimentos | G4: {=_xlfn.UNIQUE(AREAS!L2:L1048576)} -> BELA VISTA DE GOIÁS | H4: {=_xlfn.UNIQUE(AREAS!M2:M1048576)} -> GO | L4: =COUNTA(L6:L77) -> 72
B5: =COUNTA(AREAS!N2:N243) -> 242 | G5: GOIÂNIA | H5: RO | L5: Cidade | M5: Qtde | N5: Ativo | P5: ELDORADO DO CARAJAS | Q5: =COUNTIF(AREAS!L:L,Planilha2!P5) -> 1 | R5: =_xlfn.XLOOKUP(P5,AREAS!L:L,AREAS!D:D,"não") -> Ativo
G6: PORTO VELHO | H6: AL | K6: RIO BRANCO | L6: PARAGOMINAS | M6: =COUNTIF(AREAS!L:L,Planilha2!L6) -> 2 | N6: =_xlfn.XLOOKUP(L6,AREAS!L:L,AREAS!D:D,"não") -> 1 | P6: PARAUAPEBAS | Q6: 5 | R6: 0
B7: Cidades | C7: Estados (UF) | G7: CALDAS NOVAS | H7: PB | K7: ARAPIRACA | L7: FERNANDOPOLIS | M7: =COUNTIF(AREAS!L:L,Planilha2!L7) -> 1 | N7: =_xlfn.XLOOKUP(L7,AREAS!L:L,AREAS!D:D,"não") -> 1 | P7: POÇOS DE CALDAS | Q7: =COUNTIF(AREAS!L:L,Planilha2!P7) -> 2 | R7: =_xlfn.XLOOKUP(P7,AREAS!L:L,AREAS!D:D,"não") -> 0
B8: =G2 -> 75 | C8: =H2 -> 18 | G8: ARAPIRACA | H8: SE | K8: MARECHAL DEODORO | L8: ITAPETININGA | M8: =COUNTIF(AREAS!L:L,Planilha2!L8) -> 2 | N8: =_xlfn.XLOOKUP(L8,AREAS!L:L,AREAS!D:D,"não") -> 1
G9: MARECHAL DEODORO | H9: CE | K9: PENEDO | L9: ITAPETININGA | M9: =COUNTIF(AREAS!L:L,Planilha2!L9) -> 7 | N9: =_xlfn.XLOOKUP(L9,AREAS!L:L,AREAS!D:D,"não") -> 1
B10: Total de Unidades | G10: RIO LARGO | H10: MA | K10: RIO LARGO | L10: REDENÇÃO | M10: =COUNTIF(AREAS!L:L,Planilha2!L10) -> 2 | N10: =_xlfn.XLOOKUP(L10,AREAS!L:L,AREAS!D:D,"não") -> 1
B11: =SUM(AREAS!AJ2:AJ243) -> 207735.02 | G11: PENEDO | H11: PA | K11: SÃO MIGUEL DOS CAMPOS | L11: SANTARÉM | M11: =COUNTIF(AREAS!L:L,Planilha2!L11) -> 5 | N11: =_xlfn.XLOOKUP(L11,AREAS!L:L,AREAS!D:D,"não") -> 1
G12: ALAGOINHA | H12: MT | K12: ALAGOINHAS | L12: XINGUARA | M12: =COUNTIF(AREAS!L:L,Planilha2!L12) -> 1 | N12: =_xlfn.XLOOKUP(L12,AREAS!L:L,AREAS!D:D,"não") -> 1
B13: Área Total | G13: BARRA DOS COQUEIROS | H13: AC | K13: BARREIRAS | L13: SANTANA DO ARAGUAIA | M13: =COUNTIF(AREAS!L:L,Planilha2!L13) -> 7 | N13: =_xlfn.XLOOKUP(L13,AREAS!L:L,AREAS!D:D,"não") -> 1
B14: =SUM(AREAS!AC2:AC243) -> 52559402 | C14: =B14/10000 -> 5255.9402 | G14: CRATO | H14: ES | K14: CRATO | L14: OURILÂNDIA DO NORTE | M14: =COUNTIF(AREAS!L:L,Planilha2!L14) -> 1 | N14: =_xlfn.XLOOKUP(L14,AREAS!L:L,AREAS!D:D,"não") -> 1
G15: ITAPIPOCA | H15: SP | K15: ITAPIPOCA | L15: PALMAS | M15: =COUNTIF(AREAS!L:L,Planilha2!L15) -> 25 | N15: =_xlfn.XLOOKUP(L15,AREAS!L:L,AREAS!D:D,"não") -> 1
B16: VGV Total | G16: TAUÁ | H16: MG | K16: TAUÁ | L16: BARREIRAS | M16: =COUNTIF(AREAS!L:L,Planilha2!L16) -> 2 | N16: =_xlfn.XLOOKUP(L16,AREAS!L:L,AREAS!D:D,"não") -> 1
B17: =SUM(AREAS!AL2:AL243) -> 33376.909 | G17: BALSAS | H17: RJ | K17: COLATINA | L17: FORMOSA | M17: =COUNTIF(AREAS!L:L,Planilha2!L17) -> 2 | N17: =_xlfn.XLOOKUP(L17,AREAS!L:L,AREAS!D:D,"não") -> 1
B18: VGV Total BT | G18: ELDORADO DO CARAJAS | H18: RS | K18: BELA VISTA DE GOIÁS | L18: ARAPIRACA | M18: =COUNTIF(AREAS!L:L,Planilha2!L18) -> 2 | N18: =_xlfn.XLOOKUP(L18,AREAS!L:L,AREAS!D:D,"não") -> 1
B19: =SUM(AREAS!AM2:AM243) -> 20967.496 | G19: PARAGOMINAS | H19: TO | K19: CALDAS NOVAS | L19: MARECHAL DEODORO | M19: =COUNTIF(AREAS!L:L,Planilha2!L19) -> 1 | N19: =_xlfn.XLOOKUP(L19,AREAS!L:L,AREAS!D:D,"não") -> 1
G20: REDENÇÃO | H20: PR | K20: FORMOSA | L20: RIO LARGO | M20: =COUNTIF(AREAS!L:L,Planilha2!L20) -> 3 | N20: =_xlfn.XLOOKUP(L20,AREAS!L:L,AREAS!D:D,"não") -> 1
G21: SANTARÉM | H21: BA | K21: GOIÂNIA | L21: PENEDO | M21: =COUNTIF(AREAS!L:L,Planilha2!L21) -> 1 | N21: =_xlfn.XLOOKUP(L21,AREAS!L:L,AREAS!D:D,"não") -> 1
G22: XINGUARA | H22: 0 | K22: NOVO GAMA | L22: ALAGOINHA | M22: =COUNTIF(AREAS!L:L,Planilha2!L22) -> 1 | N22: =_xlfn.XLOOKUP(L22,AREAS!L:L,AREAS!D:D,"não") -> 1
G23: SANTANA DO ARAGUAIA | K23: PORANGATU | L23: BARRA DOS COQUEIROS | M23: =COUNTIF(AREAS!L:L,Planilha2!L23) -> 2 | N23: =_xlfn.XLOOKUP(L23,AREAS!L:L,AREAS!D:D,"não") -> 1
G24: OURILÂNDIA DO NORTE | K24: RIO VERDE | L24: CRATO | M24: =COUNTIF(AREAS!L:L,Planilha2!L24) -> 1 | N24: =_xlfn.XLOOKUP(L24,AREAS!L:L,AREAS!D:D,"não") -> 1
G25: PARAUAPEBAS | K25: ÁGUAS LINDAS DE GOIÁS | L25: ITAPIPOCA | M25: =COUNTIF(AREAS!L:L,Planilha2!L25) -> 2 | N25: =_xlfn.XLOOKUP(L25,AREAS!L:L,AREAS!D:D,"não") -> 1
G26: CONCEIÇÃO DO ARAGUAIA | K26: BALSAS | L26: TAUÁ | M26: =COUNTIF(AREAS!L:L,Planilha2!L26) -> 2 | N26: =_xlfn.XLOOKUP(L26,AREAS!L:L,AREAS!D:D,"não") -> 1
G27: VARZEA GRANDE | K27: MONTES CLAROS | L27: BALSAS | M27: =COUNTIF(AREAS!L:L,Planilha2!L27) -> 4 | N27: =_xlfn.XLOOKUP(L27,AREAS!L:L,AREAS!D:D,"não") -> 1
G28: RIO BRANCO | K28: NOVA SERRANA | L28: MONTES CLAROS | M28: =COUNTIF(AREAS!L:L,Planilha2!L28) -> 3 | N28: =_xlfn.XLOOKUP(L28,AREAS!L:L,AREAS!D:D,"não") -> 1
G29: CÁCERES | K29: UBERABA | L29: ITATIAIA | M29: =COUNTIF(AREAS!L:L,Planilha2!L29) -> 5 | N29: =_xlfn.XLOOKUP(L29,AREAS!L:L,AREAS!D:D,"não") -> 1
G30: TANGARÁ DA SERRA | K30: ALTA FLORESTA | L30: COLATINA | M30: =COUNTIF(AREAS!L:L,Planilha2!L30) -> 4 | N30: =_xlfn.XLOOKUP(L30,AREAS!L:L,AREAS!D:D,"não") -> 1
G31: CUIABÁ | K31: CHAPADA DOS GUIMARÃES | L31: VARGEM GRANDE | M31: =COUNTIF(AREAS!L:L,Planilha2!L31) -> 1 | N31: =_xlfn.XLOOKUP(L31,AREAS!L:L,AREAS!D:D,"não") -> 1
G32: CACOAL | K32: CUIABÁ | L32: DUQUE DE CAXIAS | M32: =COUNTIF(AREAS!L:L,Planilha2!L32) -> 4 | N32: =_xlfn.XLOOKUP(L32,AREAS!L:L,AREAS!D:D,"não") -> 1
G33: JI-PARANÁ | K33: CÁCERES | L33: LUZIMANGUES | M33: =COUNTIF(AREAS!L:L,Planilha2!L33) -> 3 | N33: =_xlfn.XLOOKUP(L33,AREAS!L:L,AREAS!D:D,"não") -> 1
G34: ROLIM DE MOURA | K34: TANGARÁ DA SERRA | L34: ITABORAÍ | M34: =COUNTIF(AREAS!L:L,Planilha2!L34) -> 2 | N34: =_xlfn.XLOOKUP(L34,AREAS!L:L,AREAS!D:D,"não") -> 1
... G36: CHAPADA DOS GUIMARÃES | K36: CANAÃ DOS CARAJÁS | L36: ARRAIAL DO CABO | M36: =COUNTIF(AREAS!L:L,Planilha2!L36) -> 2 | N36: =_xlfn.XLOOKUP(L36,AREAS!L:L,AREAS!D:D,"não") -> 1
G37: GUARANTÃ DO NORTE | K37: CONCEIÇÃO DO ARAGUAIA | L37: PARAUAPEBAS | M37: 1 | N37: =_xlfn.XLOOKUP(L37,AREAS!L:L,AREAS!D:D,"não") -> 1
G38: COLATINA | K38: ELDORADO DOS CARAJÁS | L38: PORANGATU | M38: =COUNTIF(AREAS!L:L,Planilha2!L38) -> 1 | N38: =_xlfn.XLOOKUP(L38,AREAS!L:L,AREAS!D:D,"não") -> 1
G39: FERNANDOPOLIS | K39: ITAITUBA | L39: LORENA | M39: =COUNTIF(AREAS!L:L,Planilha2!L39) -> 6 | N39: =_xlfn.XLOOKUP(L39,AREAS!L:L,AREAS!D:D,"não") -> 1
G40: ITAPETININGA | K40: MARABÁ | L40: PRESIDENTE PRUDENTE | M40: =COUNTIF(AREAS!L:L,Planilha2!L40) -> 6 | N40: =_xlfn.XLOOKUP(L40,AREAS!L:L,AREAS!D:D,"não") -> 1
G41: ITAPETININGA | K41: OURILÂNDIA DO NORTE | L41: CAÇAPAVA | M41: =COUNTIF(AREAS!L:L,Planilha2!L41) -> 1 | N41: =_xlfn.XLOOKUP(L41,AREAS!L:L,AREAS!D:D,"não") -> 1
G42: MONTES CLAROS | K42: PARAGOMINAS | L42: AVARÉ | M42: =COUNTIF(AREAS!L:L,Planilha2!L42) -> 2 | N42: =_xlfn.XLOOKUP(L42,AREAS!L:L,AREAS!D:D,"não") -> 1
G43: ITATIAIA | K43: PARAUAPEBAS | L43: RIO GRANDE DO SUL | M43: =COUNTIF(AREAS!L:L,Planilha2!L43) -> 0 | N43: =_xlfn.XLOOKUP(L43,AREAS!L:L,AREAS!D:D,"não") -> não
G44: VARGEM GRANDE | K44: REDENÇÃO | L44: RIO DE JANEIRO | M44: =COUNTIF(AREAS!L:L,Planilha2!L44) -> 1 | N44: =_xlfn.XLOOKUP(L44,AREAS!L:L,AREAS!D:D,"não") -> 1
G45: DUQUE DE CAXIAS | K45: SANTANA DO ARAGUAIA | L45: CABO FRIO | M45: =COUNTIF(AREAS!L:L,Planilha2!L45) -> 3 | N45: =_xlfn.XLOOKUP(L45,AREAS!L:L,AREAS!D:D,"não") -> 1
G46: ITABORAÍ | K46: SANTARÉM | L46: CACHOEIRA DO SUL | M46: =COUNTIF(AREAS!L:L,Planilha2!L46) -> 4 | N46: =_xlfn.XLOOKUP(L46,AREAS!L:L,AREAS!D:D,"não") -> 1
G47: MACAE | K47: TUCUMÃ | L47: GUAÍBA | M47: =COUNTIF(AREAS!L:L,Planilha2!L47) -> 5 | N47: =_xlfn.XLOOKUP(L47,AREAS!L:L,AREAS!D:D,"não") -> 1
G48: ARRAIAL DO CABO | K48: TUCURUÍ | L48: PORTO ALEGRE | M48: =COUNTIF(AREAS!L:L,Planilha2!L48) -> 12 | N48: =_xlfn.XLOOKUP(L48,AREAS!L:L,AREAS!D:D,"não") -> 1
G49: LORENA | K49: XINGUARA | L49: SANTA CRUZ DO SUL | M49: =COUNTIF(AREAS!L:L,Planilha2!L49) -> 2 | N49: =_xlfn.XLOOKUP(L49,AREAS!L:L,AREAS!D:D,"não") -> 1
... G77: LUZIMANGUES | K77: SÃO LEOPOLDO | L77: CALDAS NOVAS | M77: =COUNTIF(AREAS!L:L,Planilha2!L77) -> 1 | N77: =_xlfn.XLOOKUP(L77,AREAS!L:L,AREAS!D:D,"não") -> 1
G78: PORANGATU | K78: TORRES | M78: =SUM(M6:M77) -> 229
G79: 0 | K79: VIAMÃO
K80: BARRA DOS COQUEIROS
K81: ALVARES MACHADO
K82: AVARÉ
K83: CAÇAPAVA
K84: FERNANDÓPOLIS
K85: ITAPETININGA
K86: LORENA
K87: PRESIDENTE PRUDENTE
K88: GURUPI
K89: LUZIMANGUES
K90: PALMAS
K91: PORTO NACIONAL
